{
"meta":{"test_sets":[],"test_metrics":[],"learn_metrics":[{"best_value":"Min","name":"Logloss"}],"launch_mode":"Train","parameters":"","iteration_count":1000,"learn_sets":["learn"],"name":"experiment"},
"iterations":[
{"learn":[0.0928936245],"iteration":0,"passed_time":0.2497427301,"remaining_time":249.4929874},
{"learn":[0.08629987536],"iteration":1,"passed_time":0.3228099966,"remaining_time":161.0821883},
{"learn":[0.0784453163],"iteration":2,"passed_time":0.3957038484,"remaining_time":131.5055789},
{"learn":[0.07689752358],"iteration":3,"passed_time":0.5104924369,"remaining_time":127.1126168},
{"learn":[0.07600766724],"iteration":4,"passed_time":0.5855769475,"remaining_time":116.5298126},
{"learn":[0.0755408837],"iteration":5,"passed_time":0.6587468154,"remaining_time":109.1323891},
{"learn":[0.07472472492],"iteration":6,"passed_time":0.7291549095,"remaining_time":103.4358322},
{"learn":[0.07442028533],"iteration":7,"passed_time":0.7957025945,"remaining_time":98.66712172},
{"learn":[0.07403759678],"iteration":8,"passed_time":0.87279745,"remaining_time":96.10469699},
{"learn":[0.07352981975],"iteration":9,"passed_time":0.9406329719,"remaining_time":93.12266422},
{"learn":[0.07321597531],"iteration":10,"passed_time":1.015494182,"remaining_time":91.30215871},
{"learn":[0.07263715642],"iteration":11,"passed_time":1.08996048,"remaining_time":89.74007953},
{"learn":[0.07255595463],"iteration":12,"passed_time":1.179768737,"remaining_time":89.5716726},
{"learn":[0.07106901363],"iteration":13,"passed_time":1.262797917,"remaining_time":88.93705332},
{"learn":[0.07076993286],"iteration":14,"passed_time":1.350525904,"remaining_time":88.68453436},
{"learn":[0.07055604771],"iteration":15,"passed_time":1.430699551,"remaining_time":87.98802237},
{"learn":[0.07046110684],"iteration":16,"passed_time":1.508074204,"remaining_time":87.20217307},
{"learn":[0.07033491869],"iteration":17,"passed_time":1.588213881,"remaining_time":86.6458906},
{"learn":[0.07021293248],"iteration":18,"passed_time":1.662652297,"remaining_time":85.84536334},
{"learn":[0.07000837295],"iteration":19,"passed_time":1.750319787,"remaining_time":85.76566957},
{"learn":[0.06976775168],"iteration":20,"passed_time":1.828717299,"remaining_time":85.25305883},
{"learn":[0.06961143907],"iteration":21,"passed_time":1.907284746,"remaining_time":84.78747643},
{"learn":[0.06951356679],"iteration":22,"passed_time":1.986878449,"remaining_time":84.39914105},
{"learn":[0.06937686689],"iteration":23,"passed_time":2.074400537,"remaining_time":84.35895517},
{"learn":[0.06926831341],"iteration":24,"passed_time":2.165049407,"remaining_time":84.43692688},
{"learn":[0.06920654498],"iteration":25,"passed_time":2.245845616,"remaining_time":84.13283192},
{"learn":[0.06913056282],"iteration":26,"passed_time":2.328175094,"remaining_time":83.9005321},
{"learn":[0.06904414359],"iteration":27,"passed_time":2.411851704,"remaining_time":83.72570916},
{"learn":[0.0689479864],"iteration":28,"passed_time":2.492460151,"remaining_time":83.45444161},
{"learn":[0.0688514283],"iteration":29,"passed_time":2.558866486,"remaining_time":82.73668306},
{"learn":[0.06880546265],"iteration":30,"passed_time":2.621906555,"remaining_time":81.95572426},
{"learn":[0.06878174232],"iteration":31,"passed_time":2.686758255,"remaining_time":81.2744372},
{"learn":[0.06875696175],"iteration":32,"passed_time":2.758368713,"remaining_time":80.82856197},
{"learn":[0.0687023373],"iteration":33,"passed_time":2.830679986,"remaining_time":80.42461373},
{"learn":[0.06859193157],"iteration":34,"passed_time":2.90023973,"remaining_time":79.96375255},
{"learn":[0.06853099372],"iteration":35,"passed_time":2.973739616,"remaining_time":79.6301386},
{"learn":[0.06848902684],"iteration":36,"passed_time":3.045583547,"remaining_time":79.2674853},
{"learn":[0.06847388114],"iteration":37,"passed_time":3.110122262,"remaining_time":78.73520041},
{"learn":[0.06843056059],"iteration":38,"passed_time":3.177192119,"remaining_time":78.28927248},
{"learn":[0.06837219285],"iteration":39,"passed_time":3.247259346,"remaining_time":77.93422431},
{"learn":[0.06836081029],"iteration":40,"passed_time":3.321594838,"remaining_time":77.69291342},
{"learn":[0.06832961654],"iteration":41,"passed_time":3.383630006,"remaining_time":77.17898918},
{"learn":[0.06828633814],"iteration":42,"passed_time":3.452963364,"remaining_time":76.84851022},
{"learn":[0.06823733742],"iteration":43,"passed_time":3.522691581,"remaining_time":76.53848072},
{"learn":[0.06820756747],"iteration":44,"passed_time":3.595267724,"remaining_time":76.29957058},
{"learn":[0.06818915075],"iteration":45,"passed_time":3.660108225,"remaining_time":75.90746188},
{"learn":[0.06816297265],"iteration":46,"passed_time":3.732657972,"remaining_time":75.68559674},
{"learn":[0.06815245734],"iteration":47,"passed_time":3.808341875,"remaining_time":75.53211385},
{"learn":[0.06811725878],"iteration":48,"passed_time":3.884066297,"remaining_time":75.38259283},
{"learn":[0.0681046746],"iteration":49,"passed_time":3.954436051,"remaining_time":75.13428497},
{"learn":[0.06810479196],"iteration":50,"passed_time":4.022903818,"remaining_time":74.85756319},
{"learn":[0.06810360422],"iteration":51,"passed_time":4.087314671,"remaining_time":74.51489054},
{"learn":[0.06810225314],"iteration":52,"passed_time":4.158133596,"remaining_time":74.29721728},
{"learn":[0.06809650509],"iteration":53,"passed_time":4.228138179,"remaining_time":74.07071699},
{"learn":[0.06809631024],"iteration":54,"passed_time":4.303524472,"remaining_time":73.94237503},
{"learn":[0.06809631024],"iteration":55,"passed_time":4.377009709,"remaining_time":73.78387794},
{"learn":[0.06809631024],"iteration":56,"passed_time":4.441829197,"remaining_time":73.48499882},
{"learn":[0.06809631024],"iteration":57,"passed_time":4.509633001,"remaining_time":73.24266012},
{"learn":[0.06809631024],"iteration":58,"passed_time":4.581154331,"remaining_time":73.06552924},
{"learn":[0.06809631024],"iteration":59,"passed_time":4.658505649,"remaining_time":72.98325517},
{"learn":[0.06809631024],"iteration":60,"passed_time":4.734843636,"remaining_time":72.88554385},
{"learn":[0.06809631024],"iteration":61,"passed_time":4.811616677,"remaining_time":72.79510391},
{"learn":[0.06809631024],"iteration":62,"passed_time":4.887996063,"remaining_time":72.69924303},
{"learn":[0.06809631024],"iteration":63,"passed_time":4.969712309,"remaining_time":72.68204252},
{"learn":[0.06809631024],"iteration":64,"passed_time":5.043665914,"remaining_time":72.5511943},
{"learn":[0.06809631024],"iteration":65,"passed_time":5.118771771,"remaining_time":72.43837627},
{"learn":[0.06809631024],"iteration":66,"passed_time":5.198116777,"remaining_time":72.38571572},
{"learn":[0.06809631024],"iteration":67,"passed_time":5.278580145,"remaining_time":72.34759845},
{"learn":[0.06809631024],"iteration":68,"passed_time":5.355210861,"remaining_time":72.25654074},
{"learn":[0.06809631024],"iteration":69,"passed_time":5.432116775,"remaining_time":72.16955144},
{"learn":[0.06809631024],"iteration":70,"passed_time":5.584171017,"remaining_time":73.066125},
{"learn":[0.06809631024],"iteration":71,"passed_time":5.68067042,"remaining_time":73.21752986},
{"learn":[0.06809631024],"iteration":72,"passed_time":5.77101856,"remaining_time":73.2840302},
{"learn":[0.06809631024],"iteration":73,"passed_time":5.870761015,"remaining_time":73.46384729},
{"learn":[0.06809631024],"iteration":74,"passed_time":5.968279797,"remaining_time":73.60878416},
{"learn":[0.06809631024],"iteration":75,"passed_time":6.058899407,"remaining_time":73.66346121},
{"learn":[0.06809631024],"iteration":76,"passed_time":6.144599006,"remaining_time":73.65538809},
{"learn":[0.06809631024],"iteration":77,"passed_time":6.234104242,"remaining_time":73.69030911},
{"learn":[0.06809631024],"iteration":78,"passed_time":6.319396246,"remaining_time":73.6729613},
{"learn":[0.06809631024],"iteration":79,"passed_time":6.403387462,"remaining_time":73.63895582},
{"learn":[0.06809631024],"iteration":80,"passed_time":6.493799305,"remaining_time":73.67656249},
{"learn":[0.06809631024],"iteration":81,"passed_time":6.583229028,"remaining_time":73.70005181},
{"learn":[0.06809631024],"iteration":82,"passed_time":6.668289556,"remaining_time":73.67254847},
{"learn":[0.06809631024],"iteration":83,"passed_time":6.75100632,"remaining_time":73.61811653},
{"learn":[0.06809631024],"iteration":84,"passed_time":6.830485196,"remaining_time":73.52816417},
{"learn":[0.06809631024],"iteration":85,"passed_time":6.915069072,"remaining_time":73.49271083},
{"learn":[0.06809631024],"iteration":86,"passed_time":6.994581712,"remaining_time":73.40290923},
{"learn":[0.06809631024],"iteration":87,"passed_time":7.06982865,"remaining_time":73.26913328},
{"learn":[0.06809631024],"iteration":88,"passed_time":7.145384567,"remaining_time":73.13983528},
{"learn":[0.06809631024],"iteration":89,"passed_time":7.224074195,"remaining_time":73.04341686},
{"learn":[0.06809631024],"iteration":90,"passed_time":7.296533025,"remaining_time":72.88514856},
{"learn":[0.06809631024],"iteration":91,"passed_time":7.374366794,"remaining_time":72.78179401},
{"learn":[0.06809631024],"iteration":92,"passed_time":7.447384255,"remaining_time":72.63201634},
{"learn":[0.06809631024],"iteration":93,"passed_time":7.526244356,"remaining_time":72.54018497},
{"learn":[0.06809631024],"iteration":94,"passed_time":7.610228392,"remaining_time":72.49743889},
{"learn":[0.06809631024],"iteration":95,"passed_time":7.682738317,"remaining_time":72.34578581},
{"learn":[0.06809631024],"iteration":96,"passed_time":7.764743569,"remaining_time":72.28415921},
{"learn":[0.06809631024],"iteration":97,"passed_time":7.83788565,"remaining_time":72.14053935},
{"learn":[0.06809631024],"iteration":98,"passed_time":7.920584725,"remaining_time":72.08532159},
{"learn":[0.06809631024],"iteration":99,"passed_time":7.994783106,"remaining_time":71.95304796},
{"learn":[0.06809631024],"iteration":100,"passed_time":8.078580481,"remaining_time":71.90736488},
{"learn":[0.06809631024],"iteration":101,"passed_time":8.157019929,"remaining_time":71.81376369},
{"learn":[0.06809631024],"iteration":102,"passed_time":8.24134875,"remaining_time":71.77174591},
{"learn":[0.06809631024],"iteration":103,"passed_time":8.307646756,"remaining_time":71.57357205},
{"learn":[0.06809631024],"iteration":104,"passed_time":8.38425954,"remaining_time":71.46583132},
{"learn":[0.06809631024],"iteration":105,"passed_time":8.469890023,"remaining_time":71.43473283},
{"learn":[0.06809631024],"iteration":106,"passed_time":8.550122658,"remaining_time":71.35756573},
{"learn":[0.06809631024],"iteration":107,"passed_time":8.630112672,"remaining_time":71.27833799},
{"learn":[0.06809631024],"iteration":108,"passed_time":8.714850827,"remaining_time":71.23790905},
{"learn":[0.06809631024],"iteration":109,"passed_time":8.79928025,"remaining_time":71.19417657},
{"learn":[0.06809631024],"iteration":110,"passed_time":8.874840162,"remaining_time":71.07867481},
{"learn":[0.06809631024],"iteration":111,"passed_time":8.954023491,"remaining_time":70.99261482},
{"learn":[0.06809631024],"iteration":112,"passed_time":9.027105394,"remaining_time":70.85878304},
{"learn":[0.06809631024],"iteration":113,"passed_time":9.108636503,"remaining_time":70.7916837},
{"learn":[0.06809631024],"iteration":114,"passed_time":9.189814109,"remaining_time":70.72161293},
{"learn":[0.06809631024],"iteration":115,"passed_time":9.271006272,"remaining_time":70.65146159},
{"learn":[0.06809631024],"iteration":116,"passed_time":9.34888914,"remaining_time":70.55614624},
{"learn":[0.06809631024],"iteration":117,"passed_time":9.426709192,"remaining_time":70.46065684},
{"learn":[0.06809631024],"iteration":118,"passed_time":9.501545952,"remaining_time":70.34337801},
{"learn":[0.06809631024],"iteration":119,"passed_time":9.579094155,"remaining_time":70.24669047},
{"learn":[0.06809631024],"iteration":120,"passed_time":9.670088362,"remaining_time":70.24799727},
{"learn":[0.06809631024],"iteration":121,"passed_time":9.762163829,"remaining_time":70.25557247},
{"learn":[0.06809631024],"iteration":122,"passed_time":9.850544148,"remaining_time":70.23518063},
{"learn":[0.06809631024],"iteration":123,"passed_time":9.943690139,"remaining_time":70.24735937},
{"learn":[0.06809631024],"iteration":124,"passed_time":10.10057301,"remaining_time":70.70401107},
{"learn":[0.06809631024],"iteration":125,"passed_time":10.1913468,"remaining_time":70.69235795},
{"learn":[0.06809631024],"iteration":126,"passed_time":10.2838914,"remaining_time":70.69163144},
{"learn":[0.06809631024],"iteration":127,"passed_time":10.36872606,"remaining_time":70.63694625},
{"learn":[0.06809631024],"iteration":128,"passed_time":10.45318484,"remaining_time":70.57925576},
{"learn":[0.06809631024],"iteration":129,"passed_time":10.53134116,"remaining_time":70.47897543},
{"learn":[0.06809631024],"iteration":130,"passed_time":10.60915997,"remaining_time":70.37679398},
{"learn":[0.06809631024],"iteration":131,"passed_time":10.69063664,"remaining_time":70.29903489},
{"learn":[0.06809631024],"iteration":132,"passed_time":10.75634369,"remaining_time":70.11842091},
{"learn":[0.06809631024],"iteration":133,"passed_time":10.82312368,"remaining_time":69.946456},
{"learn":[0.06809631024],"iteration":134,"passed_time":10.8895576,"remaining_time":69.77383205},
{"learn":[0.06809631024],"iteration":135,"passed_time":10.96593671,"remaining_time":69.66595084},
{"learn":[0.06809631024],"iteration":136,"passed_time":11.03995409,"remaining_time":69.54365239},
{"learn":[0.06809631024],"iteration":137,"passed_time":11.11139893,"remaining_time":69.40598459},
{"learn":[0.06809631024],"iteration":138,"passed_time":11.18619307,"remaining_time":69.29001605},
{"learn":[0.06809631024],"iteration":139,"passed_time":11.25049412,"remaining_time":69.11017819},
{"learn":[0.06809631024],"iteration":140,"passed_time":11.31305652,"remaining_time":68.92138691},
{"learn":[0.06809631024],"iteration":141,"passed_time":11.38004868,"remaining_time":68.76113919},
{"learn":[0.06809631024],"iteration":142,"passed_time":11.4459029,"remaining_time":68.59537609},
{"learn":[0.06809631024],"iteration":143,"passed_time":11.52239854,"remaining_time":68.49425796},
{"learn":[0.06809631024],"iteration":144,"passed_time":11.5889992,"remaining_time":68.33513323},
{"learn":[0.06809631024],"iteration":145,"passed_time":11.65055642,"remaining_time":68.14777525},
{"learn":[0.06809631024],"iteration":146,"passed_time":11.72067754,"remaining_time":68.01182271},
{"learn":[0.06809631024],"iteration":147,"passed_time":11.78687537,"remaining_time":67.85417441},
{"learn":[0.06809631024],"iteration":148,"passed_time":11.8583846,"remaining_time":67.72808924},
{"learn":[0.06809631024],"iteration":149,"passed_time":11.92598054,"remaining_time":67.58055639},
{"learn":[0.06809631024],"iteration":150,"passed_time":11.98935954,"remaining_time":67.4103725},
{"learn":[0.06809631024],"iteration":151,"passed_time":12.05505176,"remaining_time":67.2544993},
{"learn":[0.06809631024],"iteration":152,"passed_time":12.11767436,"remaining_time":67.08281167},
{"learn":[0.06809631024],"iteration":153,"passed_time":12.18269214,"remaining_time":66.92569838},
{"learn":[0.06809631024],"iteration":154,"passed_time":12.25179723,"remaining_time":66.79205588},
{"learn":[0.06809631024],"iteration":155,"passed_time":12.32597951,"remaining_time":66.68670967},
{"learn":[0.06809631024],"iteration":156,"passed_time":12.38943074,"remaining_time":66.52414086},
{"learn":[0.06809631024],"iteration":157,"passed_time":12.46409419,"remaining_time":66.4225779},
{"learn":[0.06809631024],"iteration":158,"passed_time":12.53766962,"remaining_time":66.31559843},
{"learn":[0.06809631024],"iteration":159,"passed_time":12.60629903,"remaining_time":66.1830699},
{"learn":[0.06809631024],"iteration":160,"passed_time":12.67218396,"remaining_time":66.0370332},
{"learn":[0.06809631024],"iteration":161,"passed_time":12.74837446,"remaining_time":65.94529506},
{"learn":[0.06809631024],"iteration":162,"passed_time":12.82270349,"remaining_time":65.84418908},
{"learn":[0.06809631024],"iteration":163,"passed_time":12.89907567,"remaining_time":65.75382473},
{"learn":[0.06809631024],"iteration":164,"passed_time":12.97816758,"remaining_time":65.67739353},
{"learn":[0.06809631024],"iteration":165,"passed_time":13.05570246,"remaining_time":65.59310753},
{"learn":[0.06809631024],"iteration":166,"passed_time":13.1311317,"remaining_time":65.49839945},
{"learn":[0.06809631024],"iteration":167,"passed_time":13.21402455,"remaining_time":65.44088351},
{"learn":[0.06809631024],"iteration":168,"passed_time":13.29470131,"remaining_time":65.37217033},
{"learn":[0.06809631024],"iteration":169,"passed_time":13.36598342,"remaining_time":65.25744847},
{"learn":[0.06809631024],"iteration":170,"passed_time":13.44565713,"remaining_time":65.18391672},
{"learn":[0.06809631024],"iteration":171,"passed_time":13.52943961,"remaining_time":65.130093},
{"learn":[0.06809631024],"iteration":172,"passed_time":13.60470364,"remaining_time":65.03520179},
{"learn":[0.06809631024],"iteration":173,"passed_time":13.68811821,"remaining_time":64.9792278},
{"learn":[0.06809631024],"iteration":174,"passed_time":13.7955175,"remaining_time":65.03601107},
{"learn":[0.06809631024],"iteration":175,"passed_time":13.89099556,"remaining_time":65.03511558},
{"learn":[0.06809631024],"iteration":176,"passed_time":13.98369177,"remaining_time":65.02021656},
{"learn":[0.06809631024],"iteration":177,"passed_time":14.08257041,"remaining_time":65.03299367},
{"learn":[0.06809631024],"iteration":178,"passed_time":14.1768853,"remaining_time":65.02359125},
{"learn":[0.06809631024],"iteration":179,"passed_time":14.26914539,"remaining_time":65.00388455},
{"learn":[0.06809631024],"iteration":180,"passed_time":14.35102816,"remaining_time":64.93642025},
{"learn":[0.06809631024],"iteration":181,"passed_time":14.44083921,"remaining_time":64.90443117},
{"learn":[0.06809631024],"iteration":182,"passed_time":14.52396285,"remaining_time":64.84195438},
{"learn":[0.06809631024],"iteration":183,"passed_time":14.61096053,"remaining_time":64.79643363},
{"learn":[0.06809631024],"iteration":184,"passed_time":14.69591531,"remaining_time":64.74146473},
{"learn":[0.06809631024],"iteration":185,"passed_time":14.78794271,"remaining_time":64.71712564},
{"learn":[0.06809631024],"iteration":186,"passed_time":14.87878212,"remaining_time":64.68689765},
{"learn":[0.06809631024],"iteration":187,"passed_time":14.94741719,"remaining_time":64.56012105},
{"learn":[0.06809631024],"iteration":188,"passed_time":15.02581419,"remaining_time":64.47584818},
{"learn":[0.06809631024],"iteration":189,"passed_time":15.1080893,"remaining_time":64.40817018},
{"learn":[0.06809631024],"iteration":190,"passed_time":15.189603,"remaining_time":64.33711426},
{"learn":[0.06809631024],"iteration":191,"passed_time":15.26129448,"remaining_time":64.22461426},
{"learn":[0.06809631024],"iteration":192,"passed_time":15.3934319,"remaining_time":64.36528259},
{"learn":[0.06809631024],"iteration":193,"passed_time":15.4804792,"remaining_time":64.31580533},
{"learn":[0.06809631024],"iteration":194,"passed_time":15.55678701,"remaining_time":64.22160791},
{"learn":[0.06809631024],"iteration":195,"passed_time":15.63425241,"remaining_time":64.13234153},
{"learn":[0.06809631024],"iteration":196,"passed_time":15.70880507,"remaining_time":64.03132218},
{"learn":[0.06809631024],"iteration":197,"passed_time":15.78445245,"remaining_time":63.93500437},
{"learn":[0.06809631024],"iteration":198,"passed_time":15.86093614,"remaining_time":63.84226052},
{"learn":[0.06809631024],"iteration":199,"passed_time":15.9416392,"remaining_time":63.7665568},
{"learn":[0.06809631024],"iteration":200,"passed_time":16.01705948,"remaining_time":63.6698036},
{"learn":[0.06809631024],"iteration":201,"passed_time":16.09925592,"remaining_time":63.60003081},
{"learn":[0.06809631024],"iteration":202,"passed_time":16.17985003,"remaining_time":63.5238447},
{"learn":[0.06809631024],"iteration":203,"passed_time":16.26086059,"remaining_time":63.44924034},
{"learn":[0.06809631024],"iteration":204,"passed_time":16.34038068,"remaining_time":63.36879338},
{"learn":[0.06809631024],"iteration":205,"passed_time":16.4329861,"remaining_time":63.33879108},
{"learn":[0.06809631024],"iteration":206,"passed_time":16.51713645,"remaining_time":63.27579325},
{"learn":[0.06809631024],"iteration":207,"passed_time":16.60266391,"remaining_time":63.21783564},
{"learn":[0.06809631024],"iteration":208,"passed_time":16.6893707,"remaining_time":63.16407763},
{"learn":[0.06809631024],"iteration":209,"passed_time":16.77078153,"remaining_time":63.09008291},
{"learn":[0.06809631024],"iteration":210,"passed_time":16.85383197,"remaining_time":63.02214894},
{"learn":[0.06809631024],"iteration":211,"passed_time":16.9425528,"remaining_time":62.97514907},
{"learn":[0.06809631024],"iteration":212,"passed_time":17.02241405,"remaining_time":62.89502281},
{"learn":[0.06809631024],"iteration":213,"passed_time":17.09820355,"remaining_time":62.79994389},
{"learn":[0.06809631024],"iteration":214,"passed_time":17.17382265,"remaining_time":62.70442224},
{"learn":[0.06809631024],"iteration":215,"passed_time":17.25296635,"remaining_time":62.62187787},
{"learn":[0.06809631024],"iteration":216,"passed_time":17.33873761,"remaining_time":62.56327903},
{"learn":[0.06809631024],"iteration":217,"passed_time":17.41109535,"remaining_time":62.45631451},
{"learn":[0.06809631024],"iteration":218,"passed_time":17.49562518,"remaining_time":62.39307429},
{"learn":[0.06809631024],"iteration":219,"passed_time":17.57068788,"remaining_time":62.29607523},
{"learn":[0.06809631024],"iteration":220,"passed_time":17.64259536,"remaining_time":62.18815289},
{"learn":[0.06809631024],"iteration":221,"passed_time":17.7252703,"remaining_time":62.1182896},
{"learn":[0.06809631024],"iteration":222,"passed_time":17.8161544,"remaining_time":62.07691467},
{"learn":[0.06809631024],"iteration":223,"passed_time":17.89820175,"remaining_time":62.00448465},
{"learn":[0.06809631024],"iteration":224,"passed_time":17.98534008,"remaining_time":61.94950471},
{"learn":[0.06809631024],"iteration":225,"passed_time":18.06094333,"remaining_time":61.85473513},
{"learn":[0.06809631024],"iteration":226,"passed_time":18.13974709,"remaining_time":61.77103303},
{"learn":[0.06809631024],"iteration":227,"passed_time":18.21399737,"remaining_time":61.67195602},
{"learn":[0.06809631024],"iteration":228,"passed_time":18.28938995,"remaining_time":61.57694169},
{"learn":[0.06809631024],"iteration":229,"passed_time":18.36970281,"remaining_time":61.49857027},
{"learn":[0.06809631024],"iteration":230,"passed_time":18.4524792,"remaining_time":61.42838315},
{"learn":[0.06809631024],"iteration":231,"passed_time":18.53227991,"remaining_time":61.34823694},
{"learn":[0.06809631024],"iteration":232,"passed_time":18.61031966,"remaining_time":61.26229692},
{"learn":[0.06809631024],"iteration":233,"passed_time":18.68408783,"remaining_time":61.16244136},
{"learn":[0.06809631024],"iteration":234,"passed_time":18.75198493,"remaining_time":61.04369563},
{"learn":[0.06809631024],"iteration":235,"passed_time":18.81955778,"remaining_time":60.92433113},
{"learn":[0.06809631024],"iteration":236,"passed_time":18.88343264,"remaining_time":60.79349832},
{"learn":[0.06809631024],"iteration":237,"passed_time":18.95167547,"remaining_time":60.67721307},
{"learn":[0.06809631024],"iteration":238,"passed_time":19.03528871,"remaining_time":60.61027074},
{"learn":[0.06809631024],"iteration":239,"passed_time":19.11449623,"remaining_time":60.52923805},
{"learn":[0.06809631024],"iteration":240,"passed_time":19.19305369,"remaining_time":60.44617323},
{"learn":[0.06809631024],"iteration":241,"passed_time":19.26232437,"remaining_time":60.33405733},
{"learn":[0.06809631024],"iteration":242,"passed_time":19.33064934,"remaining_time":60.21934795},
{"learn":[0.06809631024],"iteration":243,"passed_time":19.40307772,"remaining_time":60.11773261},
{"learn":[0.06809631024],"iteration":244,"passed_time":19.46795754,"remaining_time":59.99309363},
{"learn":[0.06809631024],"iteration":245,"passed_time":19.53108459,"remaining_time":59.8635682},
{"learn":[0.06809631024],"iteration":246,"passed_time":19.60145359,"remaining_time":59.75665812},
{"learn":[0.06809631024],"iteration":247,"passed_time":19.67220006,"remaining_time":59.65118729},
{"learn":[0.06809631024],"iteration":248,"passed_time":19.73785099,"remaining_time":59.53062689},
{"learn":[0.06809631024],"iteration":249,"passed_time":19.80346632,"remaining_time":59.41039896},
{"learn":[0.06809631024],"iteration":250,"passed_time":19.86840984,"remaining_time":59.28860148},
{"learn":[0.06809631024],"iteration":251,"passed_time":19.93299928,"remaining_time":59.1662042},
{"learn":[0.06809631024],"iteration":252,"passed_time":20.0024493,"remaining_time":59.05861513},
{"learn":[0.06809631024],"iteration":253,"passed_time":20.07257517,"remaining_time":58.95331134},
{"learn":[0.06809631024],"iteration":254,"passed_time":20.19080593,"remaining_time":58.98882516},
{"learn":[0.06809631024],"iteration":255,"passed_time":20.25544929,"remaining_time":58.86739951},
{"learn":[0.06809631024],"iteration":256,"passed_time":20.32203863,"remaining_time":58.75204163},
{"learn":[0.06809631024],"iteration":257,"passed_time":20.40030267,"remaining_time":58.67063792},
{"learn":[0.06809631024],"iteration":258,"passed_time":20.46794321,"remaining_time":58.55886456},
{"learn":[0.06809631024],"iteration":259,"passed_time":20.53784655,"remaining_time":58.45387094},
{"learn":[0.06809631024],"iteration":260,"passed_time":20.60590486,"remaining_time":58.34392219},
{"learn":[0.06809631024],"iteration":261,"passed_time":20.67806242,"remaining_time":58.24583994},
{"learn":[0.06809631024],"iteration":262,"passed_time":20.75885874,"remaining_time":58.17216307},
{"learn":[0.06809631024],"iteration":263,"passed_time":20.83218457,"remaining_time":58.07760548},
{"learn":[0.06809631024],"iteration":264,"passed_time":20.9094692,"remaining_time":57.99418816},
{"learn":[0.06809631024],"iteration":265,"passed_time":20.98548005,"remaining_time":57.90730209},
{"learn":[0.06809631024],"iteration":266,"passed_time":21.06365009,"remaining_time":57.82642517},
{"learn":[0.06809631024],"iteration":267,"passed_time":21.13865961,"remaining_time":57.73693596},
{"learn":[0.06809631024],"iteration":268,"passed_time":21.21801731,"remaining_time":57.65937045},
{"learn":[0.06809631024],"iteration":269,"passed_time":21.2962948,"remaining_time":57.57887112},
{"learn":[0.06809631024],"iteration":270,"passed_time":21.37214686,"remaining_time":57.4918637},
{"learn":[0.06809631024],"iteration":271,"passed_time":21.45435988,"remaining_time":57.4219632},
{"learn":[0.06809631024],"iteration":272,"passed_time":21.53009432,"remaining_time":57.33472004},
{"learn":[0.06809631024],"iteration":273,"passed_time":21.60773974,"remaining_time":57.25262426},
{"learn":[0.06809631024],"iteration":274,"passed_time":21.70633183,"remaining_time":57.2257839},
{"learn":[0.06809631024],"iteration":275,"passed_time":21.80362905,"remaining_time":57.19502693},
{"learn":[0.06809631024],"iteration":276,"passed_time":21.89852075,"remaining_time":57.15751085},
{"learn":[0.06809631024],"iteration":277,"passed_time":21.99967659,"remaining_time":57.13585072},
{"learn":[0.06809631024],"iteration":278,"passed_time":22.09285175,"remaining_time":57.0929968},
{"learn":[0.06809631024],"iteration":279,"passed_time":22.18619342,"remaining_time":57.05021165},
{"learn":[0.06809631024],"iteration":280,"passed_time":22.27296315,"remaining_time":56.9902509},
{"learn":[0.06809631024],"iteration":281,"passed_time":22.364584,"remaining_time":56.94245145},
{"learn":[0.06809631024],"iteration":282,"passed_time":22.45203518,"remaining_time":56.88377816},
{"learn":[0.06809631024],"iteration":283,"passed_time":22.54427882,"remaining_time":56.83698463},
{"learn":[0.06809631024],"iteration":284,"passed_time":22.63214401,"remaining_time":56.7788876},
{"learn":[0.06809631024],"iteration":285,"passed_time":22.71252144,"remaining_time":56.70188918},
{"learn":[0.06809631024],"iteration":286,"passed_time":22.79166149,"remaining_time":56.62179318},
{"learn":[0.06809631024],"iteration":287,"passed_time":22.86874913,"remaining_time":56.53662978},
{"learn":[0.06809631024],"iteration":288,"passed_time":22.94287563,"remaining_time":56.44423729},
{"learn":[0.06809631024],"iteration":289,"passed_time":23.02268575,"remaining_time":56.3658858},
{"learn":[0.06809631024],"iteration":290,"passed_time":23.10439986,"remaining_time":56.29216323},
{"learn":[0.06809631024],"iteration":291,"passed_time":23.185623,"remaining_time":56.2171955},
{"learn":[0.06809631024],"iteration":292,"passed_time":23.26037364,"remaining_time":56.12656711},
{"learn":[0.06809631024],"iteration":293,"passed_time":23.3375713,"remaining_time":56.04192293},
{"learn":[0.06809631024],"iteration":294,"passed_time":23.41529176,"remaining_time":55.95857862},
{"learn":[0.06809631024],"iteration":295,"passed_time":23.50079902,"remaining_time":55.89379227},
{"learn":[0.06809631024],"iteration":296,"passed_time":23.57291878,"remaining_time":55.79717812},
{"learn":[0.06809631024],"iteration":297,"passed_time":23.64919747,"remaining_time":55.71052558},
{"learn":[0.06809631024],"iteration":298,"passed_time":23.71838761,"remaining_time":55.60732347},
{"learn":[0.06809631024],"iteration":299,"passed_time":23.79657934,"remaining_time":55.52535178},
{"learn":[0.06809631024],"iteration":300,"passed_time":23.86894584,"remaining_time":55.42987755},
{"learn":[0.06809631024],"iteration":301,"passed_time":23.94921336,"remaining_time":55.35281763},
{"learn":[0.06809631024],"iteration":302,"passed_time":24.0261091,"remaining_time":55.26798034},
{"learn":[0.06809631024],"iteration":303,"passed_time":24.10295894,"remaining_time":55.18309021},
{"learn":[0.06809631024],"iteration":304,"passed_time":24.18470744,"remaining_time":55.10941532},
{"learn":[0.06809631024],"iteration":305,"passed_time":24.27289232,"remaining_time":55.05028519},
{"learn":[0.06809631024],"iteration":306,"passed_time":24.35626934,"remaining_time":54.98011287},
{"learn":[0.06809631024],"iteration":307,"passed_time":24.43569373,"remaining_time":54.90097423},
{"learn":[0.06809631024],"iteration":308,"passed_time":24.52173997,"remaining_time":54.8366418},
{"learn":[0.06809631024],"iteration":309,"passed_time":24.59957337,"remaining_time":54.75388912},
{"learn":[0.06809631024],"iteration":310,"passed_time":24.68152011,"remaining_time":54.68028088},
{"learn":[0.06809631024],"iteration":311,"passed_time":24.76340001,"remaining_time":54.60647182},
{"learn":[0.06809631024],"iteration":312,"passed_time":24.84344343,"remaining_time":54.52858031},
{"learn":[0.06809631024],"iteration":313,"passed_time":24.91750997,"remaining_time":54.43761733},
{"learn":[0.06809631024],"iteration":314,"passed_time":24.99387408,"remaining_time":54.35175792},
{"learn":[0.06809631024],"iteration":315,"passed_time":25.07230544,"remaining_time":54.2704333},
{"learn":[0.06809631024],"iteration":316,"passed_time":25.14857325,"remaining_time":54.1844654},
{"learn":[0.06809631024],"iteration":317,"passed_time":25.22334464,"remaining_time":54.09534919},
{"learn":[0.06809631024],"iteration":318,"passed_time":25.29997667,"remaining_time":54.01029503},
{"learn":[0.06809631024],"iteration":319,"passed_time":25.37732893,"remaining_time":53.92682398},
{"learn":[0.06809631024],"iteration":320,"passed_time":25.461368,"remaining_time":53.85753543},
{"learn":[0.06809631024],"iteration":321,"passed_time":25.54075722,"remaining_time":53.77836459},
{"learn":[0.06809631024],"iteration":322,"passed_time":25.62003554,"remaining_time":53.69895994},
{"learn":[0.06809631024],"iteration":323,"passed_time":25.76966024,"remaining_time":53.76632815},
{"learn":[0.06809631024],"iteration":324,"passed_time":25.85687764,"remaining_time":53.70274586},
{"learn":[0.06809631024],"iteration":325,"passed_time":25.93978393,"remaining_time":53.63010542},
{"learn":[0.06809631024],"iteration":326,"passed_time":26.0212445,"remaining_time":53.55442675},
{"learn":[0.06809631024],"iteration":327,"passed_time":26.10078124,"remaining_time":53.47477132},
{"learn":[0.06809631024],"iteration":328,"passed_time":26.1748333,"remaining_time":53.38393053},
{"learn":[0.06809631024],"iteration":329,"passed_time":26.25542127,"remaining_time":53.30646137},
{"learn":[0.06809631024],"iteration":330,"passed_time":26.33718431,"remaining_time":53.23134834},
{"learn":[0.06809631024],"iteration":331,"passed_time":26.41266457,"remaining_time":53.14355401},
{"learn":[0.06809631024],"iteration":332,"passed_time":26.48643823,"remaining_time":53.05241531},
{"learn":[0.06809631024],"iteration":333,"passed_time":26.57130718,"remaining_time":52.98350473},
{"learn":[0.06809631024],"iteration":334,"passed_time":26.65294872,"remaining_time":52.90809223},
{"learn":[0.06809631024],"iteration":335,"passed_time":26.71375263,"remaining_time":52.79146353},
{"learn":[0.06809631024],"iteration":336,"passed_time":26.78237219,"remaining_time":52.69054232},
{"learn":[0.06809631024],"iteration":337,"passed_time":26.85347508,"remaining_time":52.59467605},
{"learn":[0.06809631024],"iteration":338,"passed_time":26.92322405,"remaining_time":52.49631593},
{"learn":[0.06809631024],"iteration":339,"passed_time":26.99969789,"remaining_time":52.41117826},
{"learn":[0.06809631024],"iteration":340,"passed_time":27.0770772,"remaining_time":52.32784128},
{"learn":[0.06809631024],"iteration":341,"passed_time":27.14919703,"remaining_time":52.23442001},
{"learn":[0.06809631024],"iteration":342,"passed_time":27.21411573,"remaining_time":52.12732955},
{"learn":[0.06809631024],"iteration":343,"passed_time":27.28759277,"remaining_time":52.03680481},
{"learn":[0.06809631024],"iteration":344,"passed_time":27.36108943,"remaining_time":51.94641616},
{"learn":[0.06809631024],"iteration":345,"passed_time":27.43281269,"remaining_time":51.85277311},
{"learn":[0.06809631024],"iteration":346,"passed_time":27.50744966,"remaining_time":51.76473957},
{"learn":[0.06809631024],"iteration":347,"passed_time":27.57851783,"remaining_time":51.67009663},
{"learn":[0.06809631024],"iteration":348,"passed_time":27.65050093,"remaining_time":51.57729544},
{"learn":[0.06809631024],"iteration":349,"passed_time":27.72194086,"remaining_time":51.48360446},
{"learn":[0.06809631024],"iteration":350,"passed_time":27.79279543,"remaining_time":51.38895794},
{"learn":[0.06809631024],"iteration":351,"passed_time":27.86687641,"remaining_time":51.30038613},
{"learn":[0.06809631024],"iteration":352,"passed_time":27.93403891,"remaining_time":51.1992158},
{"learn":[0.06809631024],"iteration":353,"passed_time":27.99605916,"remaining_time":51.08885372},
{"learn":[0.06809631024],"iteration":354,"passed_time":28.05681625,"remaining_time":50.97646896},
{"learn":[0.06809631024],"iteration":355,"passed_time":28.12572807,"remaining_time":50.87912606},
{"learn":[0.06809631024],"iteration":356,"passed_time":28.19354808,"remaining_time":50.77997595},
{"learn":[0.06809631024],"iteration":357,"passed_time":28.25770117,"remaining_time":50.674425},
{"learn":[0.06809631024],"iteration":358,"passed_time":28.32402014,"remaining_time":50.5729719},
{"learn":[0.06809631024],"iteration":359,"passed_time":28.39759026,"remaining_time":50.4846049},
{"learn":[0.06809631024],"iteration":360,"passed_time":28.4587798,"remaining_time":50.37440523},
{"learn":[0.06809631024],"iteration":361,"passed_time":28.5286435,"remaining_time":50.27976396},
{"learn":[0.06809631024],"iteration":362,"passed_time":28.59432744,"remaining_time":50.17792446},
{"learn":[0.06809631024],"iteration":363,"passed_time":28.66392346,"remaining_time":50.08311901},
{"learn":[0.06809631024],"iteration":364,"passed_time":28.73506781,"remaining_time":49.99114537},
{"learn":[0.06809631024],"iteration":365,"passed_time":28.81692375,"remaining_time":49.91784059},
{"learn":[0.06809631024],"iteration":366,"passed_time":28.88958132,"remaining_time":49.82862392},
{"learn":[0.06809631024],"iteration":367,"passed_time":28.96594888,"remaining_time":49.74586873},
{"learn":[0.06809631024],"iteration":368,"passed_time":29.04318901,"remaining_time":49.66464028},
{"learn":[0.06809631024],"iteration":369,"passed_time":29.11701029,"remaining_time":49.57761211},
{"learn":[0.06809631024],"iteration":370,"passed_time":29.19241424,"remaining_time":49.49333844},
{"learn":[0.06809631024],"iteration":371,"passed_time":29.27026946,"remaining_time":49.4132506},
{"learn":[0.06809631024],"iteration":372,"passed_time":29.35032787,"remaining_time":49.33687822},
{"learn":[0.06809631024],"iteration":373,"passed_time":29.42898133,"remaining_time":49.25813452},
{"learn":[0.06809631024],"iteration":374,"passed_time":29.5040479,"remaining_time":49.17341316},
{"learn":[0.06809631024],"iteration":375,"passed_time":29.58184069,"remaining_time":49.09326752},
{"learn":[0.06809631024],"iteration":376,"passed_time":29.73747724,"remaining_time":49.14177273},
{"learn":[0.06809631024],"iteration":377,"passed_time":29.84208406,"remaining_time":49.10522826},
{"learn":[0.06809631024],"iteration":378,"passed_time":29.94782741,"remaining_time":49.07018686},
{"learn":[0.06809631024],"iteration":379,"passed_time":30.06443754,"remaining_time":49.05250336},
{"learn":[0.06809631024],"iteration":380,"passed_time":30.15841185,"remaining_time":48.99752477},
{"learn":[0.06809631024],"iteration":381,"passed_time":30.25264597,"remaining_time":48.94276233},
{"learn":[0.06809631024],"iteration":382,"passed_time":30.33966644,"remaining_time":48.87617283},
{"learn":[0.06809631024],"iteration":383,"passed_time":30.42392576,"remaining_time":48.80504758},
{"learn":[0.06809631024],"iteration":384,"passed_time":30.5178664,"remaining_time":48.74931905},
{"learn":[0.06809631024],"iteration":385,"passed_time":30.60453151,"remaining_time":48.68181955},
{"learn":[0.06809631024],"iteration":386,"passed_time":30.68933532,"remaining_time":48.61127273},
{"learn":[0.06809631024],"iteration":387,"passed_time":30.76884901,"remaining_time":48.53230823},
{"learn":[0.06809631024],"iteration":388,"passed_time":30.84218113,"remaining_time":48.44363154},
{"learn":[0.06809631024],"iteration":389,"passed_time":30.9164725,"remaining_time":48.35653391},
{"learn":[0.06809631024],"iteration":390,"passed_time":30.99517638,"remaining_time":48.27637447},
{"learn":[0.06809631024],"iteration":391,"passed_time":31.06939705,"remaining_time":48.18926889},
{"learn":[0.06809631024],"iteration":392,"passed_time":31.14207546,"remaining_time":48.09984683},
{"learn":[0.06809631024],"iteration":393,"passed_time":31.21652136,"remaining_time":48.01322829},
{"learn":[0.06809631024],"iteration":394,"passed_time":31.29726321,"remaining_time":47.93631454},
{"learn":[0.06809631024],"iteration":395,"passed_time":31.37381242,"remaining_time":47.85298662},
{"learn":[0.06809631024],"iteration":396,"passed_time":31.44887075,"remaining_time":47.76742837},
{"learn":[0.06809631024],"iteration":397,"passed_time":31.52179184,"remaining_time":47.67869017},
{"learn":[0.06809631024],"iteration":398,"passed_time":31.60355834,"remaining_time":47.60335479},
{"learn":[0.06809631024],"iteration":399,"passed_time":31.67580599,"remaining_time":47.51370898},
{"learn":[0.06809631024],"iteration":400,"passed_time":31.75862351,"remaining_time":47.43993885},
{"learn":[0.06809631024],"iteration":401,"passed_time":31.82965354,"remaining_time":47.3485891},
{"learn":[0.06809631024],"iteration":402,"passed_time":31.90782194,"remaining_time":47.26791488},
{"learn":[0.06809631024],"iteration":403,"passed_time":31.98657071,"remaining_time":47.18810927},
{"learn":[0.06809631024],"iteration":404,"passed_time":32.06994862,"remaining_time":47.1151097},
{"learn":[0.06809631024],"iteration":405,"passed_time":32.15175994,"remaining_time":47.03976701},
{"learn":[0.06809631024],"iteration":406,"passed_time":32.23894156,"remaining_time":46.97221707},
{"learn":[0.06809631024],"iteration":407,"passed_time":32.32150992,"remaining_time":46.89787713},
{"learn":[0.06809631024],"iteration":408,"passed_time":32.40321513,"remaining_time":46.82224973},
{"learn":[0.06809631024],"iteration":409,"passed_time":32.4863535,"remaining_time":46.74865504},
{"learn":[0.06809631024],"iteration":410,"passed_time":32.57708568,"remaining_time":46.68589651},
{"learn":[0.06809631024],"iteration":411,"passed_time":32.65936954,"remaining_time":46.61094488},
{"learn":[0.06809631024],"iteration":412,"passed_time":32.75120046,"remaining_time":46.54952704},
{"learn":[0.06809631024],"iteration":413,"passed_time":32.84769187,"remaining_time":46.49455903},
{"learn":[0.06809631024],"iteration":414,"passed_time":32.94693718,"remaining_time":46.44327289},
{"learn":[0.06809631024],"iteration":415,"passed_time":33.04267607,"remaining_time":46.38683372},
{"learn":[0.06809631024],"iteration":416,"passed_time":33.14279015,"remaining_time":46.33632292},
{"learn":[0.06809631024],"iteration":417,"passed_time":33.22311358,"remaining_time":46.25801939},
{"learn":[0.06809631024],"iteration":418,"passed_time":33.31048881,"remaining_time":46.18948448},
{"learn":[0.06809631024],"iteration":419,"passed_time":33.39584735,"remaining_time":46.11807491},
{"learn":[0.06809631024],"iteration":420,"passed_time":33.47346928,"remaining_time":46.03595894},
{"learn":[0.06809631024],"iteration":421,"passed_time":33.55606311,"remaining_time":45.96067412},
{"learn":[0.06809631024],"iteration":422,"passed_time":33.64004444,"remaining_time":45.88724738},
{"learn":[0.06809631024],"iteration":423,"passed_time":33.73006899,"remaining_time":45.82198051},
{"learn":[0.06809631024],"iteration":424,"passed_time":33.81233825,"remaining_time":45.74610469},
{"learn":[0.06809631024],"iteration":425,"passed_time":33.89094478,"remaining_time":45.66526363},
{"learn":[0.06809631024],"iteration":426,"passed_time":33.96698601,"remaining_time":45.5809906},
{"learn":[0.06809631024],"iteration":427,"passed_time":34.04580576,"remaining_time":45.50046938},
{"learn":[0.06809631024],"iteration":428,"passed_time":34.12878172,"remaining_time":45.42548803},
{"learn":[0.06809631024],"iteration":429,"passed_time":34.20678278,"remaining_time":45.34387485},
{"learn":[0.06809631024],"iteration":430,"passed_time":34.28594383,"remaining_time":45.26380983},
{"learn":[0.06809631024],"iteration":431,"passed_time":34.36561844,"remaining_time":45.18442425},
{"learn":[0.06809631024],"iteration":432,"passed_time":34.44622862,"remaining_time":45.10626242},
{"learn":[0.06809631024],"iteration":433,"passed_time":34.52847745,"remaining_time":45.03022636},
{"learn":[0.06809631024],"iteration":434,"passed_time":34.6119015,"remaining_time":44.95568816},
{"learn":[0.06809631024],"iteration":435,"passed_time":34.74596637,"remaining_time":44.94661705},
{"learn":[0.06809631024],"iteration":436,"passed_time":34.82753006,"remaining_time":44.86933507},
{"learn":[0.06809631024],"iteration":437,"passed_time":34.90022314,"remaining_time":44.78065161},
{"learn":[0.06809631024],"iteration":438,"passed_time":34.97580912,"remaining_time":44.69573786},
{"learn":[0.06809631024],"iteration":439,"passed_time":35.05262084,"remaining_time":44.61242653},
{"learn":[0.06809631024],"iteration":440,"passed_time":35.13193251,"remaining_time":44.53231354},
{"learn":[0.06809631024],"iteration":441,"passed_time":35.21638404,"remaining_time":44.45869298},
{"learn":[0.06809631024],"iteration":442,"passed_time":35.3047032,"remaining_time":44.38988641},
{"learn":[0.06809631024],"iteration":443,"passed_time":35.37953645,"remaining_time":44.3041042},
{"learn":[0.06809631024],"iteration":444,"passed_time":35.45454497,"remaining_time":44.2185898},
{"learn":[0.06809631024],"iteration":445,"passed_time":35.52783813,"remaining_time":44.13099176},
{"learn":[0.06809631024],"iteration":446,"passed_time":35.60411578,"remaining_time":44.04714995},
{"learn":[0.06809631024],"iteration":447,"passed_time":35.67936062,"remaining_time":43.96206934},
{"learn":[0.06809631024],"iteration":448,"passed_time":35.7505688,"remaining_time":43.87207886},
{"learn":[0.06809631024],"iteration":449,"passed_time":35.81743937,"remaining_time":43.77687035},
{"learn":[0.06809631024],"iteration":450,"passed_time":35.88772621,"remaining_time":43.6859461},
{"learn":[0.06809631024],"iteration":451,"passed_time":35.9566431,"remaining_time":43.59345226},
{"learn":[0.06809631024],"iteration":452,"passed_time":36.02865591,"remaining_time":43.50480084},
{"learn":[0.06809631024],"iteration":453,"passed_time":36.10034788,"remaining_time":43.41583688},
{"learn":[0.06809631024],"iteration":454,"passed_time":36.17143677,"remaining_time":43.32622646},
{"learn":[0.06809631024],"iteration":455,"passed_time":36.24186287,"remaining_time":43.23590658},
{"learn":[0.06809631024],"iteration":456,"passed_time":36.3147828,"remaining_time":43.14863689},
{"learn":[0.06809631024],"iteration":457,"passed_time":36.38364882,"remaining_time":43.05663245},
{"learn":[0.06809631024],"iteration":458,"passed_time":36.45678778,"remaining_time":42.96976512},
{"learn":[0.06809631024],"iteration":459,"passed_time":36.53278215,"remaining_time":42.88630948},
{"learn":[0.06809631024],"iteration":460,"passed_time":36.60761785,"remaining_time":42.8015315},
{"learn":[0.06809631024],"iteration":461,"passed_time":36.67818081,"remaining_time":42.71182094},
{"learn":[0.06809631024],"iteration":462,"passed_time":36.75042967,"remaining_time":42.62414845},
{"learn":[0.06809631024],"iteration":463,"passed_time":36.83270737,"remaining_time":42.54812748},
{"learn":[0.06809631024],"iteration":464,"passed_time":36.92044186,"remaining_time":42.47835784},
{"learn":[0.06809631024],"iteration":465,"passed_time":37.00143045,"remaining_time":42.40078082},
{"learn":[0.06809631024],"iteration":466,"passed_time":37.08224807,"remaining_time":42.32299405},
{"learn":[0.06809631024],"iteration":467,"passed_time":37.15800929,"remaining_time":42.23944645},
{"learn":[0.06809631024],"iteration":468,"passed_time":37.23943977,"remaining_time":42.16235079},
{"learn":[0.06809631024],"iteration":469,"passed_time":37.31844358,"remaining_time":42.0825002},
{"learn":[0.06809631024],"iteration":470,"passed_time":37.39828109,"remaining_time":42.00358959},
{"learn":[0.06809631024],"iteration":471,"passed_time":37.47689049,"remaining_time":41.92330122},
{"learn":[0.06809631024],"iteration":472,"passed_time":37.55453236,"remaining_time":41.84194198},
{"learn":[0.06809631024],"iteration":473,"passed_time":37.63660161,"remaining_time":41.76551149},
{"learn":[0.06809631024],"iteration":474,"passed_time":37.7247753,"remaining_time":41.69580428},
{"learn":[0.06809631024],"iteration":475,"passed_time":37.82897255,"remaining_time":41.64365886},
{"learn":[0.06809631024],"iteration":476,"passed_time":37.92807121,"remaining_time":41.58570492},
{"learn":[0.06809631024],"iteration":477,"passed_time":38.02319915,"remaining_time":41.52324258},
{"learn":[0.06809631024],"iteration":478,"passed_time":38.12257006,"remaining_time":41.46525888},
{"learn":[0.06809631024],"iteration":479,"passed_time":38.21554143,"remaining_time":41.40016988},
{"learn":[0.06809631024],"iteration":480,"passed_time":38.30690987,"remaining_time":41.33323539},
{"learn":[0.06809631024],"iteration":481,"passed_time":38.39711158,"remaining_time":41.26494564},
{"learn":[0.06809631024],"iteration":482,"passed_time":38.48027357,"remaining_time":41.18902989},
{"learn":[0.06809631024],"iteration":483,"passed_time":38.57242504,"remaining_time":41.12266802},
{"learn":[0.06809631024],"iteration":484,"passed_time":38.65504736,"remaining_time":41.04608121},
{"learn":[0.06809631024],"iteration":485,"passed_time":38.75184853,"remaining_time":40.98446531},
{"learn":[0.06809631024],"iteration":486,"passed_time":38.8398226,"remaining_time":40.91340655},
{"learn":[0.06809631024],"iteration":487,"passed_time":38.92171844,"remaining_time":40.83590131},
{"learn":[0.06809631024],"iteration":488,"passed_time":38.99349078,"remaining_time":40.74779916},
{"learn":[0.06809631024],"iteration":489,"passed_time":39.06721576,"remaining_time":40.66179599},
{"learn":[0.06809631024],"iteration":490,"passed_time":39.14511798,"remaining_time":40.58017322},
{"learn":[0.06809631024],"iteration":491,"passed_time":39.221216,"remaining_time":40.4967027},
{"learn":[0.06809631024],"iteration":492,"passed_time":39.30075397,"remaining_time":40.41679972},
{"learn":[0.06809631024],"iteration":493,"passed_time":39.37848522,"remaining_time":40.33504761},
{"learn":[0.06809631024],"iteration":494,"passed_time":39.46000762,"remaining_time":40.25717949},
{"learn":[0.06809631024],"iteration":495,"passed_time":39.54322568,"remaining_time":40.18101964},
{"learn":[0.06809631024],"iteration":496,"passed_time":39.62065795,"remaining_time":40.09897575},
{"learn":[0.06809631024],"iteration":497,"passed_time":39.70392036,"remaining_time":40.02282735},
{"learn":[0.06809631024],"iteration":498,"passed_time":39.78078264,"remaining_time":39.94022466},
{"learn":[0.06809631024],"iteration":499,"passed_time":39.86373537,"remaining_time":39.86373537},
{"learn":[0.06809631024],"iteration":500,"passed_time":40.00474008,"remaining_time":39.84504052},
{"learn":[0.06809631024],"iteration":501,"passed_time":40.08488878,"remaining_time":39.76548727},
{"learn":[0.06809631024],"iteration":502,"passed_time":40.16943289,"remaining_time":39.69027465},
{"learn":[0.06809631024],"iteration":503,"passed_time":40.25114528,"remaining_time":39.61223821},
{"learn":[0.06809631024],"iteration":504,"passed_time":40.33464473,"remaining_time":39.53593889},
{"learn":[0.06809631024],"iteration":505,"passed_time":40.41829089,"remaining_time":39.45975434},
{"learn":[0.06809631024],"iteration":506,"passed_time":40.50462366,"remaining_time":39.38615279},
{"learn":[0.06809631024],"iteration":507,"passed_time":40.59212042,"remaining_time":39.31362844},
{"learn":[0.06809631024],"iteration":508,"passed_time":40.6760306,"remaining_time":39.23758551},
{"learn":[0.06809631024],"iteration":509,"passed_time":40.7561547,"remaining_time":39.15787412},
{"learn":[0.06809631024],"iteration":510,"passed_time":40.83850583,"remaining_time":39.08029227},
{"learn":[0.06809631024],"iteration":511,"passed_time":40.92406654,"remaining_time":39.00575092},
{"learn":[0.06809631024],"iteration":512,"passed_time":41.02043736,"remaining_time":38.94142884},
{"learn":[0.06809631024],"iteration":513,"passed_time":41.10029142,"remaining_time":38.86136504},
{"learn":[0.06809631024],"iteration":514,"passed_time":41.1819702,"remaining_time":38.78302048},
{"learn":[0.06809631024],"iteration":515,"passed_time":41.26309864,"remaining_time":38.70414679},
{"learn":[0.06809631024],"iteration":516,"passed_time":41.34235727,"remaining_time":38.62351753},
{"learn":[0.06809631024],"iteration":517,"passed_time":41.42141006,"remaining_time":38.54270202},
{"learn":[0.06809631024],"iteration":518,"passed_time":41.50608083,"remaining_time":38.46709996},
{"learn":[0.06809631024],"iteration":519,"passed_time":41.58382876,"remaining_time":38.3850727},
{"learn":[0.06809631024],"iteration":520,"passed_time":41.66034463,"remaining_time":38.30192913},
{"learn":[0.06809631024],"iteration":521,"passed_time":41.74233069,"remaining_time":38.22382006},
{"learn":[0.06809631024],"iteration":522,"passed_time":41.81859903,"remaining_time":38.14048133},
{"learn":[0.06809631024],"iteration":523,"passed_time":41.91112061,"remaining_time":38.07193399},
{"learn":[0.06809631024],"iteration":524,"passed_time":41.99975154,"remaining_time":37.9997752},
{"learn":[0.06809631024],"iteration":525,"passed_time":42.08560555,"remaining_time":37.92505139},
{"learn":[0.06809631024],"iteration":526,"passed_time":42.165619,"remaining_time":37.84504324},
{"learn":[0.06809631024],"iteration":527,"passed_time":42.24731936,"remaining_time":37.76654307},
{"learn":[0.06809631024],"iteration":528,"passed_time":42.32966779,"remaining_time":37.68860781},
{"learn":[0.06809631024],"iteration":529,"passed_time":42.41082517,"remaining_time":37.60959968},
{"learn":[0.06809631024],"iteration":530,"passed_time":42.49144688,"remaining_time":37.53011033},
{"learn":[0.06809631024],"iteration":531,"passed_time":42.57552966,"remaining_time":37.45366143},
{"learn":[0.06809631024],"iteration":532,"passed_time":42.6566435,"remaining_time":37.37458258},
{"learn":[0.06809631024],"iteration":533,"passed_time":42.73433525,"remaining_time":37.29250979},
{"learn":[0.06809631024],"iteration":534,"passed_time":42.81666083,"remaining_time":37.21448091},
{"learn":[0.06809631024],"iteration":535,"passed_time":42.89946228,"remaining_time":37.13684795},
{"learn":[0.06809631024],"iteration":536,"passed_time":42.97306805,"remaining_time":37.05126724},
{"learn":[0.06809631024],"iteration":537,"passed_time":43.0560044,"remaining_time":36.97374355},
{"learn":[0.06809631024],"iteration":538,"passed_time":43.13772927,"remaining_time":36.89516363},
{"learn":[0.06809631024],"iteration":539,"passed_time":43.21845126,"remaining_time":36.81571774},
{"learn":[0.06809631024],"iteration":540,"passed_time":43.29512967,"remaining_time":36.73283645},
{"learn":[0.06809631024],"iteration":541,"passed_time":43.36532631,"remaining_time":36.64450083},
{"learn":[0.06809631024],"iteration":542,"passed_time":43.43790977,"remaining_time":36.55824082},
{"learn":[0.06809631024],"iteration":543,"passed_time":43.50086495,"remaining_time":36.46396033},
{"learn":[0.06809631024],"iteration":544,"passed_time":43.5705961,"remaining_time":36.37545179},
{"learn":[0.06809631024],"iteration":545,"passed_time":43.63625097,"remaining_time":36.2836226},
{"learn":[0.06809631024],"iteration":546,"passed_time":43.70512051,"remaining_time":36.19455135},
{"learn":[0.06809631024],"iteration":547,"passed_time":43.77283238,"remaining_time":36.10459897},
{"learn":[0.06809631024],"iteration":548,"passed_time":43.83398769,"remaining_time":36.00934143},
{"learn":[0.06809631024],"iteration":549,"passed_time":43.90060583,"remaining_time":35.9186775},
{"learn":[0.06809631024],"iteration":550,"passed_time":43.97294493,"remaining_time":35.83276274},
{"learn":[0.06809631024],"iteration":551,"passed_time":44.04634887,"remaining_time":35.7477614},
{"learn":[0.06809631024],"iteration":552,"passed_time":44.11440869,"remaining_time":35.65848225},
{"learn":[0.06809631024],"iteration":553,"passed_time":44.18541906,"remaining_time":35.57165506},
{"learn":[0.06809631024],"iteration":554,"passed_time":44.26042686,"remaining_time":35.48809},
{"learn":[0.06809631024],"iteration":555,"passed_time":44.3280625,"remaining_time":35.39866862},
{"learn":[0.06809631024],"iteration":556,"passed_time":44.39837277,"remaining_time":35.31145267},
{"learn":[0.06809631024],"iteration":557,"passed_time":44.46753048,"remaining_time":35.22338436},
{"learn":[0.06809631024],"iteration":558,"passed_time":44.53728908,"remaining_time":35.13585775},
{"learn":[0.06809631024],"iteration":559,"passed_time":44.60212182,"remaining_time":35.04452429},
{"learn":[0.06809631024],"iteration":560,"passed_time":44.67828518,"remaining_time":34.96215186},
{"learn":[0.06809631024],"iteration":561,"passed_time":44.74738568,"remaining_time":34.87429702},
{"learn":[0.06809631024],"iteration":562,"passed_time":44.81977527,"remaining_time":34.7890618},
{"learn":[0.06809631024],"iteration":563,"passed_time":44.93861754,"remaining_time":34.73978236},
{"learn":[0.06809631024],"iteration":564,"passed_time":45.02984039,"remaining_time":34.66899216},
{"learn":[0.06809631024],"iteration":565,"passed_time":45.11310847,"remaining_time":34.59203017},
{"learn":[0.06809631024],"iteration":566,"passed_time":45.19401405,"remaining_time":34.51324177},
{"learn":[0.06809631024],"iteration":567,"passed_time":45.28170643,"remaining_time":34.43960771},
{"learn":[0.06809631024],"iteration":568,"passed_time":45.36276287,"remaining_time":34.36089771},
{"learn":[0.06809631024],"iteration":569,"passed_time":45.43505483,"remaining_time":34.27556768},
{"learn":[0.06809631024],"iteration":570,"passed_time":45.51002486,"remaining_time":34.19229538},
{"learn":[0.06809631024],"iteration":571,"passed_time":45.5842814,"remaining_time":34.10851825},
{"learn":[0.06809631024],"iteration":572,"passed_time":45.66272203,"remaining_time":34.02789234},
{"learn":[0.06809631024],"iteration":573,"passed_time":45.73638288,"remaining_time":33.94372666},
{"learn":[0.06809631024],"iteration":574,"passed_time":45.80994066,"remaining_time":33.85952135},
{"learn":[0.06809631024],"iteration":575,"passed_time":45.88976145,"remaining_time":33.77996329},
{"learn":[0.06809631024],"iteration":576,"passed_time":45.99361473,"remaining_time":33.71802258},
{"learn":[0.06809631024],"iteration":577,"passed_time":46.08830884,"remaining_time":33.64924971},
{"learn":[0.06809631024],"iteration":578,"passed_time":46.18902571,"remaining_time":33.58476653},
{"learn":[0.06809631024],"iteration":579,"passed_time":46.28171033,"remaining_time":33.51434196},
{"learn":[0.06809631024],"iteration":580,"passed_time":46.36707574,"remaining_time":33.43856237},
{"learn":[0.06809631024],"iteration":581,"passed_time":46.45598627,"remaining_time":33.36529598},
{"learn":[0.06809631024],"iteration":582,"passed_time":46.53613667,"remaining_time":33.2857101},
{"learn":[0.06809631024],"iteration":583,"passed_time":46.62853426,"remaining_time":33.21484632},
{"learn":[0.06809631024],"iteration":584,"passed_time":46.71655694,"remaining_time":33.14080535},
{"learn":[0.06809631024],"iteration":585,"passed_time":46.79965132,"remaining_time":33.06323489},
{"learn":[0.06809631024],"iteration":586,"passed_time":46.88834291,"remaining_time":32.98958369},
{"learn":[0.06809631024],"iteration":587,"passed_time":46.97027689,"remaining_time":32.9111464},
{"learn":[0.06809631024],"iteration":588,"passed_time":47.04558266,"remaining_time":32.82807211},
{"learn":[0.06809631024],"iteration":589,"passed_time":47.11943495,"remaining_time":32.74401412},
{"learn":[0.06809631024],"iteration":590,"passed_time":47.20719882,"remaining_time":32.66961814},
{"learn":[0.06809631024],"iteration":591,"passed_time":47.28090976,"remaining_time":32.58549186},
{"learn":[0.06809631024],"iteration":592,"passed_time":47.35866071,"remaining_time":32.50417354},
{"learn":[0.06809631024],"iteration":593,"passed_time":47.43797971,"remaining_time":32.42393899},
{"learn":[0.06809631024],"iteration":594,"passed_time":47.52307277,"remaining_time":32.34763777},
{"learn":[0.06809631024],"iteration":595,"passed_time":47.60710358,"remaining_time":32.27058699},
{"learn":[0.06809631024],"iteration":596,"passed_time":47.68740654,"remaining_time":32.19099638},
{"learn":[0.06809631024],"iteration":597,"passed_time":47.75741138,"remaining_time":32.10448056},
{"learn":[0.06809631024],"iteration":598,"passed_time":47.83580318,"remaining_time":32.02363452},
{"learn":[0.06809631024],"iteration":599,"passed_time":47.90727164,"remaining_time":31.93818109},
{"learn":[0.06809631024],"iteration":600,"passed_time":47.98511658,"remaining_time":31.85700752},
{"learn":[0.06809631024],"iteration":601,"passed_time":48.05807939,"remaining_time":31.77261727},
{"learn":[0.06809631024],"iteration":602,"passed_time":48.13464423,"remaining_time":31.69063642},
{"learn":[0.06809631024],"iteration":603,"passed_time":48.2121466,"remaining_time":31.60928817},
{"learn":[0.06809631024],"iteration":604,"passed_time":48.29189774,"remaining_time":31.52942084},
{"learn":[0.06809631024],"iteration":605,"passed_time":48.36793427,"remaining_time":31.44713879},
{"learn":[0.06809631024],"iteration":606,"passed_time":48.45370826,"remaining_time":31.37118179},
{"learn":[0.06809631024],"iteration":607,"passed_time":48.53374621,"remaining_time":31.29149426},
{"learn":[0.06809631024],"iteration":608,"passed_time":48.61176613,"remaining_time":31.21050995},
{"learn":[0.06809631024],"iteration":609,"passed_time":48.69685998,"remaining_time":31.13405802},
{"learn":[0.06809631024],"iteration":610,"passed_time":48.77492475,"remaining_time":31.05310266},
{"learn":[0.06809631024],"iteration":611,"passed_time":48.84973874,"remaining_time":30.9700958},
{"learn":[0.06809631024],"iteration":612,"passed_time":48.92829289,"remaining_time":30.88947691},
{"learn":[0.06809631024],"iteration":613,"passed_time":49.00748087,"remaining_time":30.80926322},
{"learn":[0.06809631024],"iteration":614,"passed_time":49.0915426,"remaining_time":30.7321039},
{"learn":[0.06809631024],"iteration":615,"passed_time":49.17176188,"remaining_time":30.65252689},
{"learn":[0.06809631024],"iteration":616,"passed_time":49.25929413,"remaining_time":30.57748728},
{"learn":[0.06809631024],"iteration":617,"passed_time":49.34271471,"remaining_time":30.49986573},
{"learn":[0.06809631024],"iteration":618,"passed_time":49.42184131,"remaining_time":30.41958245},
{"learn":[0.06809631024],"iteration":619,"passed_time":49.50043261,"remaining_time":30.33897482},
{"learn":[0.06809631024],"iteration":620,"passed_time":49.57731548,"remaining_time":30.25733102},
{"learn":[0.06809631024],"iteration":621,"passed_time":49.65612987,"remaining_time":30.17687635},
{"learn":[0.06809631024],"iteration":622,"passed_time":49.73638225,"remaining_time":30.09729713},
{"learn":[0.06809631024],"iteration":623,"passed_time":49.81616194,"remaining_time":30.01743091},
{"learn":[0.06809631024],"iteration":624,"passed_time":49.89989769,"remaining_time":29.93993861},
{"learn":[0.06809631024],"iteration":625,"passed_time":49.98363258,"remaining_time":29.86242585},
{"learn":[0.06809631024],"iteration":626,"passed_time":50.06011207,"remaining_time":29.78057703},
{"learn":[0.06809631024],"iteration":627,"passed_time":50.1356459,"remaining_time":29.69818515},
{"learn":[0.06809631024],"iteration":628,"passed_time":50.21844096,"remaining_time":29.62009793},
{"learn":[0.06809631024],"iteration":629,"passed_time":50.36080397,"remaining_time":29.57698011},
{"learn":[0.06809631024],"iteration":630,"passed_time":50.44262061,"remaining_time":29.49814106},
{"learn":[0.06809631024],"iteration":631,"passed_time":50.51996998,"remaining_time":29.41669138},
{"learn":[0.06809631024],"iteration":632,"passed_time":50.59719156,"remaining_time":29.33518057},
{"learn":[0.06809631024],"iteration":633,"passed_time":50.67558768,"remaining_time":29.25436134},
{"learn":[0.06809631024],"iteration":634,"passed_time":50.75626808,"remaining_time":29.17486275},
{"learn":[0.06809631024],"iteration":635,"passed_time":50.82577471,"remaining_time":29.0889654},
{"learn":[0.06809631024],"iteration":636,"passed_time":50.89454306,"remaining_time":29.00269879},
{"learn":[0.06809631024],"iteration":637,"passed_time":50.96730364,"remaining_time":28.91875222},
{"learn":[0.06809631024],"iteration":638,"passed_time":51.03990522,"remaining_time":28.83475084},
{"learn":[0.06809631024],"iteration":639,"passed_time":51.10563634,"remaining_time":28.74692044},
{"learn":[0.06809631024],"iteration":640,"passed_time":51.18338065,"remaining_time":28.66588713},
{"learn":[0.06809631024],"iteration":641,"passed_time":51.25612185,"remaining_time":28.58207418},
{"learn":[0.06809631024],"iteration":642,"passed_time":51.32909453,"remaining_time":28.49842418},
{"learn":[0.06809631024],"iteration":643,"passed_time":51.40215021,"remaining_time":28.41485322},
{"learn":[0.06809631024],"iteration":644,"passed_time":51.46691803,"remaining_time":28.32675334},
{"learn":[0.06809631024],"iteration":645,"passed_time":51.53031908,"remaining_time":28.23797671},
{"learn":[0.06809631024],"iteration":646,"passed_time":51.59315124,"remaining_time":28.14896814},
{"learn":[0.06809631024],"iteration":647,"passed_time":51.66146447,"remaining_time":28.06301773},
{"learn":[0.06809631024],"iteration":648,"passed_time":51.7358035,"remaining_time":27.98038063},
{"learn":[0.06809631024],"iteration":649,"passed_time":51.8116899,"remaining_time":27.89860226},
{"learn":[0.06809631024],"iteration":650,"passed_time":51.87847667,"remaining_time":27.81196368},
{"learn":[0.06809631024],"iteration":651,"passed_time":51.94482474,"remaining_time":27.72515186},
{"learn":[0.06809631024],"iteration":652,"passed_time":52.01233836,"remaining_time":27.63902207},
{"learn":[0.06809631024],"iteration":653,"passed_time":52.08806348,"remaining_time":27.55729352},
{"learn":[0.06809631024],"iteration":654,"passed_time":52.15142895,"remaining_time":27.46907326},
{"learn":[0.06809631024],"iteration":655,"passed_time":52.22107866,"remaining_time":27.38422417},
{"learn":[0.06809631024],"iteration":656,"passed_time":52.28665149,"remaining_time":27.29729294},
{"learn":[0.06809631024],"iteration":657,"passed_time":52.36124898,"remaining_time":27.21511725},
{"learn":[0.06809631024],"iteration":658,"passed_time":52.43561621,"remaining_time":27.13284541},
{"learn":[0.06809631024],"iteration":659,"passed_time":52.50291881,"remaining_time":27.04695818},
{"learn":[0.06809631024],"iteration":660,"passed_time":52.57228988,"remaining_time":26.962188},
{"learn":[0.06809631024],"iteration":661,"passed_time":52.63355032,"remaining_time":26.87332327},
{"learn":[0.06809631024],"iteration":662,"passed_time":52.69725774,"remaining_time":26.78578561},
{"learn":[0.06809631024],"iteration":663,"passed_time":52.76521526,"remaining_time":26.70047037},
{"learn":[0.06809631024],"iteration":664,"passed_time":52.832273,"remaining_time":26.61475407},
{"learn":[0.06809631024],"iteration":665,"passed_time":52.90486528,"remaining_time":26.53186937},
{"learn":[0.06809631024],"iteration":666,"passed_time":52.98046733,"remaining_time":26.45051817},
{"learn":[0.06809631024],"iteration":667,"passed_time":53.05497281,"remaining_time":26.36863918},
{"learn":[0.06809631024],"iteration":668,"passed_time":53.13551563,"remaining_time":26.28976932},
{"learn":[0.06809631024],"iteration":669,"passed_time":53.21318047,"remaining_time":26.20947695},
{"learn":[0.06809631024],"iteration":670,"passed_time":53.2928641,"remaining_time":26.13018225},
{"learn":[0.06809631024],"iteration":671,"passed_time":53.3763519,"remaining_time":26.05274319},
{"learn":[0.06809631024],"iteration":672,"passed_time":53.45834349,"remaining_time":25.97455917},
{"learn":[0.06809631024],"iteration":673,"passed_time":53.53641653,"remaining_time":25.89446853},
{"learn":[0.06809631024],"iteration":674,"passed_time":53.61688546,"remaining_time":25.81553744},
{"learn":[0.06809631024],"iteration":675,"passed_time":53.69491136,"remaining_time":25.73543089},
{"learn":[0.06809631024],"iteration":676,"passed_time":53.77443508,"remaining_time":25.6560451},
{"learn":[0.06809631024],"iteration":677,"passed_time":53.86958985,"remaining_time":25.58408249},
{"learn":[0.06809631024],"iteration":678,"passed_time":53.97136962,"remaining_time":25.51518358},
{"learn":[0.06809631024],"iteration":679,"passed_time":54.0736139,"remaining_time":25.44640654},
{"learn":[0.06809631024],"iteration":680,"passed_time":54.18454659,"remaining_time":25.38160112},
{"learn":[0.06809631024],"iteration":681,"passed_time":54.27782841,"remaining_time":25.30843025},
{"learn":[0.06809631024],"iteration":682,"passed_time":54.38998548,"remaining_time":25.24396105},
{"learn":[0.06809631024],"iteration":683,"passed_time":54.49967714,"remaining_time":25.17821341},
{"learn":[0.06809631024],"iteration":684,"passed_time":54.61399627,"remaining_time":25.11446544},
{"learn":[0.06809631024],"iteration":685,"passed_time":54.71961466,"remaining_time":25.04658747},
{"learn":[0.06809631024],"iteration":686,"passed_time":54.81668003,"remaining_time":24.97470284},
{"learn":[0.06809631024],"iteration":687,"passed_time":54.91258519,"remaining_time":24.90221886},
{"learn":[0.06809631024],"iteration":688,"passed_time":55.00177002,"remaining_time":24.82663349},
{"learn":[0.06809631024],"iteration":689,"passed_time":55.09739309,"remaining_time":24.75390124},
{"learn":[0.06809631024],"iteration":690,"passed_time":55.17786309,"remaining_time":24.67432662},
{"learn":[0.06809631024],"iteration":691,"passed_time":55.26355544,"remaining_time":24.59707381},
{"learn":[0.06809631024],"iteration":692,"passed_time":55.41204066,"remaining_time":24.54761397},
{"learn":[0.06809631024],"iteration":693,"passed_time":55.49382685,"remaining_time":24.46845968},
{"learn":[0.06809631024],"iteration":694,"passed_time":55.57690452,"remaining_time":24.38986457},
{"learn":[0.06809631024],"iteration":695,"passed_time":55.66364179,"remaining_time":24.31285504},
{"learn":[0.06809631024],"iteration":696,"passed_time":55.74891612,"remaining_time":24.23518161},
{"learn":[0.06809631024],"iteration":697,"passed_time":55.83797527,"remaining_time":24.15912397},
{"learn":[0.06809631024],"iteration":698,"passed_time":55.91296456,"remaining_time":24.07697043},
{"learn":[0.06809631024],"iteration":699,"passed_time":55.99596582,"remaining_time":23.99827106},
{"learn":[0.06809631024],"iteration":700,"passed_time":56.07204636,"remaining_time":23.91660751},
{"learn":[0.06809631024],"iteration":701,"passed_time":56.1801221,"remaining_time":23.84854186},
{"learn":[0.06809631024],"iteration":702,"passed_time":56.30809801,"remaining_time":23.78876972},
{"learn":[0.06809631024],"iteration":703,"passed_time":56.41082813,"remaining_time":23.7181891},
{"learn":[0.06809631024],"iteration":704,"passed_time":56.4982861,"remaining_time":23.64112681},
{"learn":[0.06809631024],"iteration":705,"passed_time":56.58421121,"remaining_time":23.56339674},
{"learn":[0.06809631024],"iteration":706,"passed_time":56.67144067,"remaining_time":23.48618404},
{"learn":[0.06809631024],"iteration":707,"passed_time":56.76170988,"remaining_time":23.41019673},
{"learn":[0.06809631024],"iteration":708,"passed_time":56.84834501,"remaining_time":23.33267757},
{"learn":[0.06809631024],"iteration":709,"passed_time":56.93816791,"remaining_time":23.25643478},
{"learn":[0.06809631024],"iteration":710,"passed_time":57.03240207,"remaining_time":23.18194683},
{"learn":[0.06809631024],"iteration":711,"passed_time":57.11446771,"remaining_time":23.10248132},
{"learn":[0.06809631024],"iteration":712,"passed_time":57.19953831,"remaining_time":23.02421809},
{"learn":[0.06809631024],"iteration":713,"passed_time":57.29140568,"remaining_time":22.9486583},
{"learn":[0.06809631024],"iteration":714,"passed_time":57.3981695,"remaining_time":22.87899064},
{"learn":[0.06809631024],"iteration":715,"passed_time":57.48030578,"remaining_time":22.79945089},
{"learn":[0.06809631024],"iteration":716,"passed_time":57.5626043,"remaining_time":22.71996794},
{"learn":[0.06809631024],"iteration":717,"passed_time":57.64852142,"remaining_time":22.64189838},
{"learn":[0.06809631024],"iteration":718,"passed_time":57.73339858,"remaining_time":22.56340056},
{"learn":[0.06809631024],"iteration":719,"passed_time":57.81502215,"remaining_time":22.48361972},
{"learn":[0.06809631024],"iteration":720,"passed_time":58.0008088,"remaining_time":22.44414099},
{"learn":[0.06809631024],"iteration":721,"passed_time":58.12540093,"remaining_time":22.38069454},
{"learn":[0.06809631024],"iteration":722,"passed_time":58.22025652,"remaining_time":22.30568611},
{"learn":[0.06809631024],"iteration":723,"passed_time":58.33207414,"remaining_time":22.23708904},
{"learn":[0.06809631024],"iteration":724,"passed_time":58.44710998,"remaining_time":22.16959344},
{"learn":[0.06809631024],"iteration":725,"passed_time":58.55759721,"remaining_time":22.10025019},
{"learn":[0.06809631024],"iteration":726,"passed_time":58.67292408,"remaining_time":22.03261111},
{"learn":[0.06809631024],"iteration":727,"passed_time":58.7795242,"remaining_time":21.96158047},
{"learn":[0.06809631024],"iteration":728,"passed_time":58.8707461,"remaining_time":21.88473552},
{"learn":[0.06809631024],"iteration":729,"passed_time":58.96634744,"remaining_time":21.80947097},
{"learn":[0.06809631024],"iteration":730,"passed_time":59.0462108,"remaining_time":21.72835938},
{"learn":[0.06809631024],"iteration":731,"passed_time":59.13746407,"remaining_time":21.65142127},
{"learn":[0.06809631024],"iteration":732,"passed_time":59.23147377,"remaining_time":21.57544815},
{"learn":[0.06809631024],"iteration":733,"passed_time":59.31619798,"remaining_time":21.49606085},
{"learn":[0.06809631024],"iteration":734,"passed_time":59.39954953,"remaining_time":21.41616412},
{"learn":[0.06809631024],"iteration":735,"passed_time":59.50193744,"remaining_time":21.34308625},
{"learn":[0.06809631024],"iteration":736,"passed_time":59.58825971,"remaining_time":21.2641958},
{"learn":[0.06809631024],"iteration":737,"passed_time":59.66292501,"remaining_time":21.18114682},
{"learn":[0.06809631024],"iteration":738,"passed_time":59.73466598,"remaining_time":21.09708771},
{"learn":[0.06809631024],"iteration":739,"passed_time":59.80993071,"remaining_time":21.01429998},
{"learn":[0.06809631024],"iteration":740,"passed_time":59.88875867,"remaining_time":20.932778},
{"learn":[0.06809631024],"iteration":741,"passed_time":59.94982345,"remaining_time":20.84508686},
{"learn":[0.06809631024],"iteration":742,"passed_time":60.02787546,"remaining_time":20.76334319},
{"learn":[0.06809631024],"iteration":743,"passed_time":60.09262083,"remaining_time":20.67703082},
{"learn":[0.06809631024],"iteration":744,"passed_time":60.17199697,"remaining_time":20.5957842},
{"learn":[0.06809631024],"iteration":745,"passed_time":60.23892428,"remaining_time":20.51030398},
{"learn":[0.06809631024],"iteration":746,"passed_time":60.29929085,"remaining_time":20.42265139},
{"learn":[0.06809631024],"iteration":747,"passed_time":60.35874395,"remaining_time":20.334764},
{"learn":[0.06809631024],"iteration":748,"passed_time":60.42398968,"remaining_time":20.24889374},
{"learn":[0.06809631024],"iteration":749,"passed_time":60.49607496,"remaining_time":20.16535832},
{"learn":[0.06809631024],"iteration":750,"passed_time":60.56400965,"remaining_time":20.08047724},
{"learn":[0.06809631024],"iteration":751,"passed_time":60.69253801,"remaining_time":20.01562424},
{"learn":[0.06809631024],"iteration":752,"passed_time":60.76202203,"remaining_time":19.93123432},
{"learn":[0.06809631024],"iteration":753,"passed_time":60.83391579,"remaining_time":19.84767014},
{"learn":[0.06809631024],"iteration":754,"passed_time":60.90245155,"remaining_time":19.76304719},
{"learn":[0.06809631024],"iteration":755,"passed_time":60.96989864,"remaining_time":19.67811543},
{"learn":[0.06809631024],"iteration":756,"passed_time":61.03786583,"remaining_time":19.59339683},
{"learn":[0.06809631024],"iteration":757,"passed_time":61.09982764,"remaining_time":19.50680513},
{"learn":[0.06809631024],"iteration":758,"passed_time":61.20246583,"remaining_time":19.43319402},
{"learn":[0.06809631024],"iteration":759,"passed_time":61.28062828,"remaining_time":19.35177735},
{"learn":[0.06809631024],"iteration":760,"passed_time":61.35834908,"remaining_time":19.27023053},
{"learn":[0.06809631024],"iteration":761,"passed_time":61.43415164,"remaining_time":19.18809461},
{"learn":[0.06809631024],"iteration":762,"passed_time":61.50843603,"remaining_time":19.10550372},
{"learn":[0.06809631024],"iteration":763,"passed_time":61.58483754,"remaining_time":19.02358856},
{"learn":[0.06809631024],"iteration":764,"passed_time":61.66395179,"remaining_time":18.94252114},
{"learn":[0.06809631024],"iteration":765,"passed_time":61.74433712,"remaining_time":18.86184711},
{"learn":[0.06809631024],"iteration":766,"passed_time":61.82644197,"remaining_time":18.78169619},
{"learn":[0.06809631024],"iteration":767,"passed_time":61.90539555,"remaining_time":18.70058824},
{"learn":[0.06809631024],"iteration":768,"passed_time":61.98099853,"remaining_time":18.6184794},
{"learn":[0.06809631024],"iteration":769,"passed_time":62.05390373,"remaining_time":18.53558163},
{"learn":[0.06809631024],"iteration":770,"passed_time":62.13535777,"remaining_time":18.45524893},
{"learn":[0.06809631024],"iteration":771,"passed_time":62.21240148,"remaining_time":18.3736108},
{"learn":[0.06809631024],"iteration":772,"passed_time":62.29036069,"remaining_time":18.2922534},
{"learn":[0.06809631024],"iteration":773,"passed_time":62.36666518,"remaining_time":18.21042162},
{"learn":[0.06809631024],"iteration":774,"passed_time":62.4784761,"remaining_time":18.13891242},
{"learn":[0.06809631024],"iteration":775,"passed_time":62.5718104,"remaining_time":18.06196589},
{"learn":[0.06809631024],"iteration":776,"passed_time":62.66843359,"remaining_time":17.9859211},
{"learn":[0.06809631024],"iteration":777,"passed_time":62.76668402,"remaining_time":17.91028773},
{"learn":[0.06809631024],"iteration":778,"passed_time":62.86338086,"remaining_time":17.83415555},
{"learn":[0.06809631024],"iteration":779,"passed_time":62.96533257,"remaining_time":17.75945278},
{"learn":[0.06809631024],"iteration":780,"passed_time":63.06890753,"remaining_time":17.6851354},
{"learn":[0.06809631024],"iteration":781,"passed_time":63.17889538,"remaining_time":17.61253094},
{"learn":[0.06809631024],"iteration":782,"passed_time":63.26330956,"remaining_time":17.53274352},
{"learn":[0.06809631024],"iteration":783,"passed_time":63.3310998,"remaining_time":17.44836423},
{"learn":[0.06809631024],"iteration":784,"passed_time":63.40120892,"remaining_time":17.36466232},
{"learn":[0.06809631024],"iteration":785,"passed_time":63.46928414,"remaining_time":17.28044123},
{"learn":[0.06809631024],"iteration":786,"passed_time":63.53933546,"remaining_time":17.196796},
{"learn":[0.06809631024],"iteration":787,"passed_time":63.6079427,"remaining_time":17.11279677},
{"learn":[0.06809631024],"iteration":788,"passed_time":63.67659216,"remaining_time":17.02884784},
{"learn":[0.06809631024],"iteration":789,"passed_time":63.75023365,"remaining_time":16.94626464},
{"learn":[0.06809631024],"iteration":790,"passed_time":63.82365064,"remaining_time":16.86364473},
{"learn":[0.06809631024],"iteration":791,"passed_time":63.89273617,"remaining_time":16.77991051},
{"learn":[0.06809631024],"iteration":792,"passed_time":63.96315873,"remaining_time":16.69656224},
{"learn":[0.06809631024],"iteration":793,"passed_time":64.0359777,"remaining_time":16.61386827},
{"learn":[0.06809631024],"iteration":794,"passed_time":64.10810185,"remaining_time":16.53101997},
{"learn":[0.06809631024],"iteration":795,"passed_time":64.17938508,"remaining_time":16.44798311},
{"learn":[0.06809631024],"iteration":796,"passed_time":64.25566656,"remaining_time":16.36624882},
{"learn":[0.06809631024],"iteration":797,"passed_time":64.32985109,"remaining_time":16.28399739},
{"learn":[0.06809631024],"iteration":798,"passed_time":64.42365695,"remaining_time":16.20670219},
{"learn":[0.06809631024],"iteration":799,"passed_time":64.49150301,"remaining_time":16.12287575},
{"learn":[0.06809631024],"iteration":800,"passed_time":64.55983045,"remaining_time":16.03920881},
{"learn":[0.06809631024],"iteration":801,"passed_time":64.62881108,"remaining_time":15.95574139},
{"learn":[0.06809631024],"iteration":802,"passed_time":64.69864059,"remaining_time":15.8725183},
{"learn":[0.06809631024],"iteration":803,"passed_time":64.77045812,"remaining_time":15.78981317},
{"learn":[0.06809631024],"iteration":804,"passed_time":64.83912616,"remaining_time":15.70637218},
{"learn":[0.06809631024],"iteration":805,"passed_time":64.90848045,"remaining_time":15.62313301},
{"learn":[0.06809631024],"iteration":806,"passed_time":64.97755594,"remaining_time":15.53986158},
{"learn":[0.06809631024],"iteration":807,"passed_time":65.05511688,"remaining_time":15.45864164},
{"learn":[0.06809631024],"iteration":808,"passed_time":65.14008914,"remaining_time":15.3791805},
{"learn":[0.06809631024],"iteration":809,"passed_time":65.21945019,"remaining_time":15.29838955},
{"learn":[0.06809631024],"iteration":810,"passed_time":65.30445639,"remaining_time":15.2189177},
{"learn":[0.06809631024],"iteration":811,"passed_time":65.39646193,"remaining_time":15.14105276},
{"learn":[0.06809631024],"iteration":812,"passed_time":65.48276964,"remaining_time":15.06184246},
{"learn":[0.06809631024],"iteration":813,"passed_time":65.55867596,"remaining_time":14.980238},
{"learn":[0.06809631024],"iteration":814,"passed_time":65.63705728,"remaining_time":14.89920932},
{"learn":[0.06809631024],"iteration":815,"passed_time":65.71733368,"remaining_time":14.81861446},
{"learn":[0.06809631024],"iteration":816,"passed_time":65.79235971,"remaining_time":14.73684434},
{"learn":[0.06809631024],"iteration":817,"passed_time":65.87092609,"remaining_time":14.65587842},
{"learn":[0.06809631024],"iteration":818,"passed_time":65.95080745,"remaining_time":14.57520897},
{"learn":[0.06809631024],"iteration":819,"passed_time":66.02709504,"remaining_time":14.49375257},
{"learn":[0.06809631024],"iteration":820,"passed_time":66.10063537,"remaining_time":14.41170978},
{"learn":[0.06809631024],"iteration":821,"passed_time":66.17660753,"remaining_time":14.33021428},
{"learn":[0.06809631024],"iteration":822,"passed_time":66.25463466,"remaining_time":14.24917416},
{"learn":[0.06809631024],"iteration":823,"passed_time":66.32814207,"remaining_time":14.16717598},
{"learn":[0.06809631024],"iteration":824,"passed_time":66.4559644,"remaining_time":14.09671972},
{"learn":[0.06809631024],"iteration":825,"passed_time":66.53218332,"remaining_time":14.01525411},
{"learn":[0.06809631024],"iteration":826,"passed_time":66.61499232,"remaining_time":13.93517977},
{"learn":[0.06809631024],"iteration":827,"passed_time":66.69562173,"remaining_time":13.85464606},
{"learn":[0.06809631024],"iteration":828,"passed_time":66.76713012,"remaining_time":13.7722307},
{"learn":[0.06809631024],"iteration":829,"passed_time":66.83922859,"remaining_time":13.68996248},
{"learn":[0.06809631024],"iteration":830,"passed_time":66.91603074,"remaining_time":13.60867532},
{"learn":[0.06809631024],"iteration":831,"passed_time":66.98984425,"remaining_time":13.52679547},
{"learn":[0.06809631024],"iteration":832,"passed_time":67.06710988,"remaining_time":13.44562707},
{"learn":[0.06809631024],"iteration":833,"passed_time":67.13934995,"remaining_time":13.36346774},
{"learn":[0.06809631024],"iteration":834,"passed_time":67.21921237,"remaining_time":13.28283837},
{"learn":[0.06809631024],"iteration":835,"passed_time":67.29849103,"remaining_time":13.20209633},
{"learn":[0.06809631024],"iteration":836,"passed_time":67.37800412,"remaining_time":13.12140343},
{"learn":[0.06809631024],"iteration":837,"passed_time":67.4577751,"remaining_time":13.04076321},
{"learn":[0.06809631024],"iteration":838,"passed_time":67.53719954,"remaining_time":12.96005855},
{"learn":[0.06809631024],"iteration":839,"passed_time":67.61616351,"remaining_time":12.87926924},
{"learn":[0.06809631024],"iteration":840,"passed_time":67.69415591,"remaining_time":12.79830058},
{"learn":[0.06809631024],"iteration":841,"passed_time":67.77263366,"remaining_time":12.71743007},
{"learn":[0.06809631024],"iteration":842,"passed_time":67.84577371,"remaining_time":12.63557114},
{"learn":[0.06809631024],"iteration":843,"passed_time":67.91742756,"remaining_time":12.55345817},
{"learn":[0.06809631024],"iteration":844,"passed_time":67.99889497,"remaining_time":12.47317008},
{"learn":[0.06809631024],"iteration":845,"passed_time":68.07484912,"remaining_time":12.39187561},
{"learn":[0.06809631024],"iteration":846,"passed_time":68.14295136,"remaining_time":12.30917539},
{"learn":[0.06809631024],"iteration":847,"passed_time":68.21409075,"remaining_time":12.227054},
{"learn":[0.06809631024],"iteration":848,"passed_time":68.29227767,"remaining_time":12.14621193},
{"learn":[0.06809631024],"iteration":849,"passed_time":68.36266861,"remaining_time":12.06400034},
{"learn":[0.06809631024],"iteration":850,"passed_time":68.4318557,"remaining_time":11.98160576},
{"learn":[0.06809631024],"iteration":851,"passed_time":68.50341087,"remaining_time":11.89965353},
{"learn":[0.06809631024],"iteration":852,"passed_time":68.57180495,"remaining_time":11.81718092},
{"learn":[0.06809631024],"iteration":853,"passed_time":68.64542948,"remaining_time":11.73563548},
{"learn":[0.06809631024],"iteration":854,"passed_time":68.72279823,"remaining_time":11.65474356},
{"learn":[0.06809631024],"iteration":855,"passed_time":68.80257137,"remaining_time":11.57426434},
{"learn":[0.06809631024],"iteration":856,"passed_time":68.88310974,"remaining_time":11.49391446},
{"learn":[0.06809631024],"iteration":857,"passed_time":68.95528964,"remaining_time":11.4121808},
{"learn":[0.06809631024],"iteration":858,"passed_time":69.03237139,"remaining_time":11.331274},
{"learn":[0.06809631024],"iteration":859,"passed_time":69.10726569,"remaining_time":11.25002},
{"learn":[0.06809631024],"iteration":860,"passed_time":69.186589,"remaining_time":11.16949578},
{"learn":[0.06809631024],"iteration":861,"passed_time":69.27076586,"remaining_time":11.08975138},
{"learn":[0.06809631024],"iteration":862,"passed_time":69.34611217,"remaining_time":11.00859486},
{"learn":[0.06809631024],"iteration":863,"passed_time":69.42424002,"remaining_time":10.92788963},
{"learn":[0.06809631024],"iteration":864,"passed_time":69.50484918,"remaining_time":10.84757762},
{"learn":[0.06809631024],"iteration":865,"passed_time":69.58643136,"remaining_time":10.76741548},
{"learn":[0.06809631024],"iteration":866,"passed_time":69.66325343,"remaining_time":10.68651985},
{"learn":[0.06809631024],"iteration":867,"passed_time":69.73654329,"remaining_time":10.60509644},
{"learn":[0.06809631024],"iteration":868,"passed_time":69.80877133,"remaining_time":10.5235317},
{"learn":[0.06809631024],"iteration":869,"passed_time":69.88541551,"remaining_time":10.44264829},
{"learn":[0.06809631024],"iteration":870,"passed_time":69.96909549,"remaining_time":10.36281667},
{"learn":[0.06809631024],"iteration":871,"passed_time":70.04939499,"remaining_time":10.28248},
{"learn":[0.06809631024],"iteration":872,"passed_time":70.1268703,"remaining_time":10.20173256},
{"learn":[0.06809631024],"iteration":873,"passed_time":70.20297579,"remaining_time":10.12079514},
{"learn":[0.06809631024],"iteration":874,"passed_time":70.28086275,"remaining_time":10.04012325},
{"learn":[0.06809631024],"iteration":875,"passed_time":70.35337499,"remaining_time":9.958696917},
{"learn":[0.06809631024],"iteration":876,"passed_time":70.42307897,"remaining_time":9.87689705},
{"learn":[0.06809631024],"iteration":877,"passed_time":70.50053595,"remaining_time":9.796202033},
{"learn":[0.06809631024],"iteration":878,"passed_time":70.58120912,"remaining_time":9.715957115},
{"learn":[0.06809631024],"iteration":879,"passed_time":70.65893575,"remaining_time":9.635309421},
{"learn":[0.06809631024],"iteration":880,"passed_time":70.73638875,"remaining_time":9.554631397},
{"learn":[0.06809631024],"iteration":881,"passed_time":70.81067287,"remaining_time":9.473536733},
{"learn":[0.06809631024],"iteration":882,"passed_time":70.94685738,"remaining_time":9.400659471},
{"learn":[0.06809631024],"iteration":883,"passed_time":71.02702007,"remaining_time":9.320287701},
{"learn":[0.06809631024],"iteration":884,"passed_time":71.10491551,"remaining_time":9.239621789},
{"learn":[0.06809631024],"iteration":885,"passed_time":71.18037191,"remaining_time":9.158648305},
{"learn":[0.06809631024],"iteration":886,"passed_time":71.25021361,"remaining_time":9.076971971},
{"learn":[0.06809631024],"iteration":887,"passed_time":71.32089844,"remaining_time":8.995428632},
{"learn":[0.06809631024],"iteration":888,"passed_time":71.40299402,"remaining_time":8.915334462},
{"learn":[0.06809631024],"iteration":889,"passed_time":71.47527633,"remaining_time":8.834022917},
{"learn":[0.06809631024],"iteration":890,"passed_time":71.54472479,"remaining_time":8.752384963},
{"learn":[0.06809631024],"iteration":891,"passed_time":71.61972662,"remaining_time":8.671446721},
{"learn":[0.06809631024],"iteration":892,"passed_time":71.69446405,"remaining_time":8.590490094},
{"learn":[0.06809631024],"iteration":893,"passed_time":71.77795909,"remaining_time":8.510585753},
{"learn":[0.06809631024],"iteration":894,"passed_time":71.85346787,"remaining_time":8.429736454},
{"learn":[0.06809631024],"iteration":895,"passed_time":71.93549074,"remaining_time":8.349655175},
{"learn":[0.06809631024],"iteration":896,"passed_time":72.021614,"remaining_time":8.270040404},
{"learn":[0.06809631024],"iteration":897,"passed_time":72.10012189,"remaining_time":8.189546139},
{"learn":[0.06809631024],"iteration":898,"passed_time":72.18120446,"remaining_time":8.109345551},
{"learn":[0.06809631024],"iteration":899,"passed_time":72.25963067,"remaining_time":8.028847852},
{"learn":[0.06809631024],"iteration":900,"passed_time":72.3266986,"remaining_time":7.947106727},
{"learn":[0.06809631024],"iteration":901,"passed_time":72.41213485,"remaining_time":7.867393809},
{"learn":[0.06809631024],"iteration":902,"passed_time":72.48552889,"remaining_time":7.786374643},
{"learn":[0.06809631024],"iteration":903,"passed_time":72.56174358,"remaining_time":7.705671885},
{"learn":[0.06809631024],"iteration":904,"passed_time":72.63551461,"remaining_time":7.624722528},
{"learn":[0.06809631024],"iteration":905,"passed_time":72.71478379,"remaining_time":7.544359466},
{"learn":[0.06809631024],"iteration":906,"passed_time":72.78597783,"remaining_time":7.463170825},
{"learn":[0.06809631024],"iteration":907,"passed_time":72.85817657,"remaining_time":7.382105996},
{"learn":[0.06809631024],"iteration":908,"passed_time":72.93584481,"remaining_time":7.301608226},
{"learn":[0.06809631024],"iteration":909,"passed_time":73.01200092,"remaining_time":7.220967124},
{"learn":[0.06809631024],"iteration":910,"passed_time":73.08412318,"remaining_time":7.139941781},
{"learn":[0.06809631024],"iteration":911,"passed_time":73.16838165,"remaining_time":7.060107002},
{"learn":[0.06809631024],"iteration":912,"passed_time":73.2445622,"remaining_time":6.979492784},
{"learn":[0.06809631024],"iteration":913,"passed_time":73.32757746,"remaining_time":6.899531358},
{"learn":[0.06809631024],"iteration":914,"passed_time":73.40669847,"remaining_time":6.819201497},
{"learn":[0.06809631024],"iteration":915,"passed_time":73.48519193,"remaining_time":6.738816727},
{"learn":[0.06809631024],"iteration":916,"passed_time":73.55913797,"remaining_time":6.658024483},
{"learn":[0.06809631024],"iteration":917,"passed_time":73.63790481,"remaining_time":6.577677771},
{"learn":[0.06809631024],"iteration":918,"passed_time":73.71787773,"remaining_time":6.497440801},
{"learn":[0.06809631024],"iteration":919,"passed_time":73.79707949,"remaining_time":6.417137347},
{"learn":[0.06809631024],"iteration":920,"passed_time":73.87613961,"remaining_time":6.336824136},
{"learn":[0.06809631024],"iteration":921,"passed_time":73.95045786,"remaining_time":6.256112487},
{"learn":[0.06809631024],"iteration":922,"passed_time":74.02528383,"remaining_time":6.175457048},
{"learn":[0.06809631024],"iteration":923,"passed_time":74.09851295,"remaining_time":6.094682883},
{"learn":[0.06809631024],"iteration":924,"passed_time":74.18092378,"remaining_time":6.014669496},
{"learn":[0.06809631024],"iteration":925,"passed_time":74.2512084,"remaining_time":5.933681881},
{"learn":[0.06809631024],"iteration":926,"passed_time":74.32440762,"remaining_time":5.852946878},
{"learn":[0.06809631024],"iteration":927,"passed_time":74.39519459,"remaining_time":5.77204096},
{"learn":[0.06809631024],"iteration":928,"passed_time":74.47268688,"remaining_time":5.691669288},
{"learn":[0.06809631024],"iteration":929,"passed_time":74.550771,"remaining_time":5.611348355},
{"learn":[0.06809631024],"iteration":930,"passed_time":74.62822632,"remaining_time":5.530985624},
{"learn":[0.06809631024],"iteration":931,"passed_time":74.70805655,"remaining_time":5.450802409},
{"learn":[0.06809631024],"iteration":932,"passed_time":74.78706515,"remaining_time":5.370560948},
{"learn":[0.06809631024],"iteration":933,"passed_time":74.86514901,"remaining_time":5.290256782},
{"learn":[0.06809631024],"iteration":934,"passed_time":74.94707738,"remaining_time":5.210224631},
{"learn":[0.06809631024],"iteration":935,"passed_time":75.01735799,"remaining_time":5.129391999},
{"learn":[0.06809631024],"iteration":936,"passed_time":75.09306242,"remaining_time":5.048946566},
{"learn":[0.06809631024],"iteration":937,"passed_time":75.16469198,"remaining_time":4.9682419},
{"learn":[0.06809631024],"iteration":938,"passed_time":75.23244655,"remaining_time":4.887304835},
{"learn":[0.06809631024],"iteration":939,"passed_time":75.30603463,"remaining_time":4.806768168},
{"learn":[0.06809631024],"iteration":940,"passed_time":75.37688811,"remaining_time":4.726074812},
{"learn":[0.06809631024],"iteration":941,"passed_time":75.44947685,"remaining_time":4.64550919},
{"learn":[0.06809631024],"iteration":942,"passed_time":75.52147929,"remaining_time":4.564925047},
{"learn":[0.06809631024],"iteration":943,"passed_time":75.60233792,"remaining_time":4.484884453},
{"learn":[0.06809631024],"iteration":944,"passed_time":75.68226516,"remaining_time":4.404787919},
{"learn":[0.06809631024],"iteration":945,"passed_time":75.75203359,"remaining_time":4.324111854},
{"learn":[0.06809631024],"iteration":946,"passed_time":75.82282119,"remaining_time":4.243515864},
{"learn":[0.06809631024],"iteration":947,"passed_time":75.89484408,"remaining_time":4.163008325},
{"learn":[0.06809631024],"iteration":948,"passed_time":75.97059693,"remaining_time":4.082719118},
{"learn":[0.06809631024],"iteration":949,"passed_time":76.04641614,"remaining_time":4.002442955},
{"learn":[0.06809631024],"iteration":950,"passed_time":76.12414524,"remaining_time":3.922274571},
{"learn":[0.06809631024],"iteration":951,"passed_time":76.18993316,"remaining_time":3.841509235},
{"learn":[0.06809631024],"iteration":952,"passed_time":76.25382455,"remaining_time":3.760681798},
{"learn":[0.06809631024],"iteration":953,"passed_time":76.35749788,"remaining_time":3.681808074},
{"learn":[0.06809631024],"iteration":954,"passed_time":76.44937228,"remaining_time":3.602326442},
{"learn":[0.06809631024],"iteration":955,"passed_time":76.53745237,"remaining_time":3.522644251},
{"learn":[0.06809631024],"iteration":956,"passed_time":76.61736548,"remaining_time":3.44257755},
{"learn":[0.06809631024],"iteration":957,"passed_time":76.70582882,"remaining_time":3.362886023},
{"learn":[0.06809631024],"iteration":958,"passed_time":76.78879732,"remaining_time":3.282941283},
{"learn":[0.06809631024],"iteration":959,"passed_time":76.86302902,"remaining_time":3.202626209},
{"learn":[0.06809631024],"iteration":960,"passed_time":76.93306121,"remaining_time":3.122153369},
{"learn":[0.06809631024],"iteration":961,"passed_time":77.00005181,"remaining_time":3.041582088},
{"learn":[0.06809631024],"iteration":962,"passed_time":77.0774889,"remaining_time":2.961440384},
{"learn":[0.06809631024],"iteration":963,"passed_time":77.15994194,"remaining_time":2.881491608},
{"learn":[0.06809631024],"iteration":964,"passed_time":77.23609501,"remaining_time":2.801309145},
{"learn":[0.06809631024],"iteration":965,"passed_time":77.31270373,"remaining_time":2.721151063},
{"learn":[0.06809631024],"iteration":966,"passed_time":77.38860246,"remaining_time":2.640976092},
{"learn":[0.06809631024],"iteration":967,"passed_time":77.45770212,"remaining_time":2.560585194},
{"learn":[0.06809631024],"iteration":968,"passed_time":77.54161467,"remaining_time":2.480691491},
{"learn":[0.06809631024],"iteration":969,"passed_time":77.62059173,"remaining_time":2.400636858},
{"learn":[0.06809631024],"iteration":970,"passed_time":77.70061078,"remaining_time":2.320615564},
{"learn":[0.06809631024],"iteration":971,"passed_time":77.77428782,"remaining_time":2.240411583},
{"learn":[0.06809631024],"iteration":972,"passed_time":77.85722883,"remaining_time":2.160478087},
{"learn":[0.06809631024],"iteration":973,"passed_time":77.93506255,"remaining_time":2.08040208},
{"learn":[0.06809631024],"iteration":974,"passed_time":78.01498837,"remaining_time":2.000384317},
{"learn":[0.06809631024],"iteration":975,"passed_time":78.08611147,"remaining_time":1.920150282},
{"learn":[0.06809631024],"iteration":976,"passed_time":78.16835039,"remaining_time":1.84019658},
{"learn":[0.06809631024],"iteration":977,"passed_time":78.24643942,"remaining_time":1.760144854},
{"learn":[0.06809631024],"iteration":978,"passed_time":78.32298252,"remaining_time":1.680063976},
{"learn":[0.06809631024],"iteration":979,"passed_time":78.39818176,"remaining_time":1.599962893},
{"learn":[0.06809631024],"iteration":980,"passed_time":78.47205657,"remaining_time":1.519846152},
{"learn":[0.06809631024],"iteration":981,"passed_time":78.55247224,"remaining_time":1.439862017},
{"learn":[0.06809631024],"iteration":982,"passed_time":78.63182751,"remaining_time":1.359858665},
{"learn":[0.06809631024],"iteration":983,"passed_time":78.70719994,"remaining_time":1.279791869},
{"learn":[0.06809631024],"iteration":984,"passed_time":78.78590781,"remaining_time":1.199785398},
{"learn":[0.06809631024],"iteration":985,"passed_time":78.85402052,"remaining_time":1.119631123},
{"learn":[0.06809631024],"iteration":986,"passed_time":78.93142521,"remaining_time":1.039623635},
{"learn":[0.06809631024],"iteration":987,"passed_time":79.00968241,"remaining_time":0.9596317701},
{"learn":[0.06809631024],"iteration":988,"passed_time":79.08197549,"remaining_time":0.8795770783},
{"learn":[0.06809631024],"iteration":989,"passed_time":79.15731908,"remaining_time":0.7995688796},
{"learn":[0.06809631024],"iteration":990,"passed_time":79.22977717,"remaining_time":0.7195438895},
{"learn":[0.06809631024],"iteration":991,"passed_time":79.30104905,"remaining_time":0.6395245891},
{"learn":[0.06809631024],"iteration":992,"passed_time":79.3736174,"remaining_time":0.5595320461},
{"learn":[0.06809631024],"iteration":993,"passed_time":79.44564402,"remaining_time":0.4795511711},
{"learn":[0.06809631024],"iteration":994,"passed_time":79.52315134,"remaining_time":0.3996138258},
{"learn":[0.06809631024],"iteration":995,"passed_time":79.59857957,"remaining_time":0.3196730103},
{"learn":[0.06809631024],"iteration":996,"passed_time":79.66592949,"remaining_time":0.2397169393},
{"learn":[0.06809631024],"iteration":997,"passed_time":79.73551999,"remaining_time":0.1597906212},
{"learn":[0.06809631024],"iteration":998,"passed_time":79.80363997,"remaining_time":0.0798835235},
{"learn":[0.06809631024],"iteration":999,"passed_time":79.87394057,"remaining_time":0}
]}